{
  "AIGCDescription": "",
  "BAInfo": "",
  "CategoryType": 120,
  "adAuthorization": false,
  "adLabelVersion": 0,
  "aigcLabelType": 0,
  "author": {
    "avatarLarger": "https://p16-sign-useast2a.tiktokcdn.com/tos-useast2a-avt-0068-euttp/3223d35959015c2cdab51bafafc49c71~c5_1080x1080.jpeg?lk3s=a5d48078&nonce=80487&refresh_token=1b7758eb68a2c1c93fb12d08d9aee7ef&x-expires=1733180400&x-signature=Dc45J5POvIWzeEjBqxG%2BmWZXxRk%3D&shp=a5d48078&shcp=b59d6b55",
    "avatarMedium": "https://p16-sign-useast2a.tiktokcdn.com/tos-useast2a-avt-0068-euttp/3223d35959015c2cdab51bafafc49c71~c5_720x720.jpeg?lk3s=a5d48078&nonce=39391&refresh_token=c91b690fcd92f07397db0d89f14714c8&x-expires=1733180400&x-signature=6%2Bq2tbJuB0MEQU914vDRDt%2BGoB4%3D&shp=a5d48078&shcp=b59d6b55",
    "avatarThumb": "https://p16-sign-useast2a.tiktokcdn.com/tos-useast2a-avt-0068-euttp/3223d35959015c2cdab51bafafc49c71~c5_100x100.jpeg?lk3s=a5d48078&nonce=35467&refresh_token=ab23c75c2e7873f868c119cab61e46ab&x-expires=1733180400&x-signature=03W6fNt4o5qEOFxAasxDPrx8Wn4%3D&shp=a5d48078&shcp=b59d6b55",
    "commentSetting": 0,
    "downloadSetting": 0,
    "duetSetting": 0,
    "ftc": false,
    "id": "7348374590534943776",
    "isADVirtual": false,
    "isEmbedBanned": false,
    "nickname": "agentul_spy_Romania",
    "openFavorite": false,
    "privateAccount": false,
    "relation": 0,
    "secUid": "MS4wLjABAAAAW7qwoOajVvXLXtZQQsEtDjoTpurdKMXRkBl164FSnS922zy-nPeEBEqvL2ht9nCF",
    "secret": false,
    "signature": "multumesc din suflet pt 100 k🎉🎉(road to 200k)🙏🙏",
    "stitchSetting": 0,
    "ttSeller": false,
    "uniqueId": "agentul_spy_romania",
    "verified": false
  },
  "authorStats": {
    "diggCount": 914,
    "followerCount": 174800,
    "followingCount": 81,
    "friendCount": 0,
    "heart": 8400000,
    "heartCount": 8400000,
    "videoCount": 1442
  },
  "challenges": [
    {
      "coverLarger": "",
      "coverMedium": "",
      "coverThumb": "",
      "desc": "",
      "id": "38807099",
      "isCommerce": false,
      "profileLarger": "",
      "profileMedium": "",
      "profileThumb": "",
      "stats": {
        "videoCount": 0,
        "viewCount": 0
      },
      "title": "2018"
    },
    {
      "coverLarger": "",
      "coverMedium": "",
      "coverThumb": "",
      "desc": "",
      "id": "151602",
      "isCommerce": false,
      "profileLarger": "",
      "profileMedium": "",
      "profileThumb": "",
      "stats": {
        "videoCount": 0,
        "viewCount": 0
      },
      "title": "goviral"
    },
    {
      "coverLarger": "https://p16-amd-va.tiktokcdn.com/obj/musically-maliva-obj/8e4d8102460a60717c89acc2d6367a16.png?shp=b59d6b55&shcp=-",
      "coverMedium": "https://p16-amd-va.tiktokcdn.com/obj/musically-maliva-obj/8e4d8102460a60717c89acc2d6367a16.png?shp=b59d6b55&shcp=-",
      "coverThumb": "https://p16-amd-va.tiktokcdn.com/obj/musically-maliva-obj/8e4d8102460a60717c89acc2d6367a16.png?shp=b59d6b55&shcp=-",
      "desc": "¡descubre las canciones en tendencia! 🔥➡️ https://bit.ly/TendenciasTikTok_LATAM",
      "id": "20884",
      "isCommerce": false,
      "profileLarger": "https://p16-amd-va.tiktokcdn.com/obj/musically-maliva-obj/4321dd2ed3acc737461c4254f0c55add.png?shp=b59d6b55&shcp=-",
      "profileMedium": "https://p16-amd-va.tiktokcdn.com/obj/musically-maliva-obj/4321dd2ed3acc737461c4254f0c55add.png?shp=b59d6b55&shcp=-",
      "profileThumb": "https://p16-amd-va.tiktokcdn.com/obj/musically-maliva-obj/4321dd2ed3acc737461c4254f0c55add.png?shp=b59d6b55&shcp=-",
      "stats": {
        "videoCount": 0,
        "viewCount": 0
      },
      "title": "viral"
    },
    {
      "coverLarger": "",
      "coverMedium": "",
      "coverThumb": "",
      "desc": "",
      "id": "1649192195281926",
      "isCommerce": false,
      "profileLarger": "",
      "profileMedium": "",
      "profileThumb": "",
      "stats": {
        "videoCount": 0,
        "viewCount": 0
      },
      "title": "romaniaviral"
    },
    {
      "coverLarger": "",
      "coverMedium": "",
      "coverThumb": "",
      "desc": "",
      "id": "42164",
      "isCommerce": false,
      "profileLarger": "",
      "profileMedium": "",
      "profileThumb": "",
      "stats": {
        "videoCount": 0,
        "viewCount": 0
      },
      "title": "foryou"
    },
    {
      "coverLarger": "",
      "coverMedium": "",
      "coverThumb": "",
      "desc": "",
      "id": "1604302285252613",
      "isCommerce": false,
      "profileLarger": "",
      "profileMedium": "",
      "profileThumb": "",
      "stats": {
        "videoCount": 0,
        "viewCount": 0
      },
      "title": "fypage"
    },
    {
      "coverLarger": "",
      "coverMedium": "",
      "coverThumb": "",
      "desc": "",
      "id": "88764338",
      "isCommerce": false,
      "profileLarger": "",
      "profileMedium": "",
      "profileThumb": "",
      "stats": {
        "videoCount": 0,
        "viewCount": 0
      },
      "title": "foryoupage"
    }
  ],
  "collected": false,
  "contents": [
    {
      "desc": "#2018 #goviral #viral #romaniaviral #foryou #fypage #foryoupage ",
      "textExtra": [
        {
          "awemeId": "",
          "end": 5,
          "hashtagId": "38807099",
          "hashtagName": "2018",
          "isCommerce": false,
          "secUid": "",
          "start": 0,
          "subType": 0,
          "type": 1,
          "userId": "",
          "userUniqueId": ""
        },
        {
          "awemeId": "",
          "end": 14,
          "hashtagId": "151602",
          "hashtagName": "goviral",
          "isCommerce": false,
          "secUid": "",
          "start": 6,
          "subType": 0,
          "type": 1,
          "userId": "",
          "userUniqueId": ""
        },
        {
          "awemeId": "",
          "end": 21,
          "hashtagId": "20884",
          "hashtagName": "viral",
          "isCommerce": false,
          "secUid": "",
          "start": 15,
          "subType": 0,
          "type": 1,
          "userId": "",
          "userUniqueId": ""
        },
        {
          "awemeId": "",
          "end": 35,
          "hashtagId": "1649192195281926",
          "hashtagName": "romaniaviral",
          "isCommerce": false,
          "secUid": "",
          "start": 22,
          "subType": 0,
          "type": 1,
          "userId": "",
          "userUniqueId": ""
        },
        {
          "awemeId": "",
          "end": 43,
          "hashtagId": "42164",
          "hashtagName": "foryou",
          "isCommerce": false,
          "secUid": "",
          "start": 36,
          "subType": 0,
          "type": 1,
          "userId": "",
          "userUniqueId": ""
        },
        {
          "awemeId": "",
          "end": 51,
          "hashtagId": "1604302285252613",
          "hashtagName": "fypage",
          "isCommerce": false,
          "secUid": "",
          "start": 44,
          "subType": 0,
          "type": 1,
          "userId": "",
          "userUniqueId": ""
        },
        {
          "awemeId": "",
          "end": 63,
          "hashtagId": "88764338",
          "hashtagName": "foryoupage",
          "isCommerce": false,
          "secUid": "",
          "start": 52,
          "subType": 0,
          "type": 1,
          "userId": "",
          "userUniqueId": ""
        }
      ]
    }
  ],
  "createTime": 1732953448,
  "desc": "#2018 #goviral #viral #romaniaviral #foryou #fypage #foryoupage ",
  "digged": false,
  "diversificationId": 10083,
  "duetDisplay": 0,
  "duetEnabled": true,
  "duetInfo": {
    "duetFromId": "0"
  },
  "forFriend": false,
  "id": "7442978238504127777",
  "isAd": false,
  "itemCommentStatus": 0,
  "itemMute": false,
  "item_control": {
    "can_repost": true
  },
  "music": {
    "album": "Movie Soundtrack Epic",
    "authorName": "DDProduction",
    "coverLarge": "https://p77-sg.tiktokcdn.com/aweme/720x720/tos-alisg-v-2774/oUIAjk2tnBbAfgZaDFICHeDALZnyI8AASb2QaD.jpeg",
    "coverMedium": "https://p77-sg.tiktokcdn.com/aweme/200x200/tos-alisg-v-2774/oUIAjk2tnBbAfgZaDFICHeDALZnyI8AASb2QaD.jpeg",
    "coverThumb": "https://p77-sg.tiktokcdn.com/aweme/100x100/tos-alisg-v-2774/oUIAjk2tnBbAfgZaDFICHeDALZnyI8AASb2QaD.jpeg",
    "duration": 253,
    "id": "7376315145117812777",
    "original": false,
    "playUrl": "https://sf16-ies-music-sg.tiktokcdn.com/obj/tos-alisg-ve-2774/oQ4P3f7KCAEgqfAif4YqIZxedgPOAwmN8v8110",
    "title": "Movie Soundtrack Epic"
  },
  "officalItem": false,
  "originalItem": false,
  "playlistId": "",
  "privateItem": false,
  "secret": false,
  "shareEnabled": true,
  "showNotPass": false,
  "stats": {
    "collectCount": 3771,
    "commentCount": 1496,
    "diggCount": 51100,
    "playCount": 567000,
    "shareCount": 4463
  },
  "statsV2": {
    "collectCount": "3771",
    "commentCount": "1496",
    "diggCount": "51101",
    "playCount": "566981",
    "repostCount": "0",
    "shareCount": "4463"
  },
  "stickersOnItem": [
    {
      "stickerText": [
        "\"am fost intr-o piata la Satu Mare si voiam sa cumpar marar....\"",
        "Ascultati cu atentie!"
      ],
      "stickerType": 4
    }
  ],
  "stitchDisplay": 0,
  "stitchEnabled": true,
  "textExtra": [
    {
      "awemeId": "",
      "end": 5,
      "hashtagId": "38807099",
      "hashtagName": "2018",
      "isCommerce": false,
      "secUid": "",
      "start": 0,
      "subType": 0,
      "type": 1,
      "userId": "",
      "userUniqueId": ""
    },
    {
      "awemeId": "",
      "end": 14,
      "hashtagId": "151602",
      "hashtagName": "goviral",
      "isCommerce": false,
      "secUid": "",
      "start": 6,
      "subType": 0,
      "type": 1,
      "userId": "",
      "userUniqueId": ""
    },
    {
      "awemeId": "",
      "end": 21,
      "hashtagId": "20884",
      "hashtagName": "viral",
      "isCommerce": false,
      "secUid": "",
      "start": 15,
      "subType": 0,
      "type": 1,
      "userId": "",
      "userUniqueId": ""
    },
    {
      "awemeId": "",
      "end": 35,
      "hashtagId": "1649192195281926",
      "hashtagName": "romaniaviral",
      "isCommerce": false,
      "secUid": "",
      "start": 22,
      "subType": 0,
      "type": 1,
      "userId": "",
      "userUniqueId": ""
    },
    {
      "awemeId": "",
      "end": 43,
      "hashtagId": "42164",
      "hashtagName": "foryou",
      "isCommerce": false,
      "secUid": "",
      "start": 36,
      "subType": 0,
      "type": 1,
      "userId": "",
      "userUniqueId": ""
    },
    {
      "awemeId": "",
      "end": 51,
      "hashtagId": "1604302285252613",
      "hashtagName": "fypage",
      "isCommerce": false,
      "secUid": "",
      "start": 44,
      "subType": 0,
      "type": 1,
      "userId": "",
      "userUniqueId": ""
    },
    {
      "awemeId": "",
      "end": 63,
      "hashtagId": "88764338",
      "hashtagName": "foryoupage",
      "isCommerce": false,
      "secUid": "",
      "start": 52,
      "subType": 0,
      "type": 1,
      "userId": "",
      "userUniqueId": ""
    }
  ],
  "video": {
    "VQScore": "72.62",
    "bitrate": 288561,
    "bitrateInfo": [
      {
        "Bitrate": 288561,
        "CodecType": "h264",
        "GearName": "normal_540_0",
        "MVMAF": "\"{\\\"v2.0\\\": {\\\"srv1\\\": {\\\"v1080\\\": 93.646, \\\"v960\\\": 96.817, \\\"v864\\\": 98.086, \\\"v720\\\": 98.417}, \\\"ori\\\": {\\\"v1080\\\": 82.267, \\\"v960\\\": 86.987, \\\"v864\\\": 89.296, \\\"v720\\\": 91.608}}}\"",
        "PlayAddr": {
          "DataSize": 3883566,
          "FileCs": "c:0-89869-9f1f",
          "FileHash": "a882d3e15f8b56d90a6e8963d82d4cdd",
          "Height": 1024,
          "Uri": "v0f044gc0000ct5caffog65lu37p7s5g",
          "UrlKey": "v0f044gc0000ct5caffog65lu37p7s5g_h264_540p_288561",
          "UrlList": [
            "https://v16-webapp-prime.tiktok.com/video/tos/useast2a/tos-useast2a-ve-0068c001-euttp/oEYELfsKTQcRDVDEQerEA9BPxDSFI7dZn8U4tB/?a=1988&bti=NDU3ZjAwOg%3D%3D&ch=0&cr=3&dr=0&lr=all&cd=0%7C0%7C0%7C&cv=1&br=562&bt=281&cs=0&ds=6&ft=4fUEKMT88Zmo0AJNjb4jVovrrpWrKsd.&mime_type=video_mp4&qs=0&rc=OzdpZzdoO2Q1NWZlNjw6O0BpanZzNm85cmlmdzMzZjczM0A1YTFgLjQwXy8xL15gLmEtYSMyNDRyMmRjXjJgLS1kMWNzcw%3D%3D&btag=e00090000&expire=1733181993&l=20241130232444DAC94285ABBC8AD03578&ply_type=2&policy=2&signature=a65f4b6149b758d958607dd48e2d0477&tk=tt_chain_token",
            "https://v19-webapp-prime.tiktok.com/video/tos/useast2a/tos-useast2a-ve-0068c001-euttp/oEYELfsKTQcRDVDEQerEA9BPxDSFI7dZn8U4tB/?a=1988&bti=NDU3ZjAwOg%3D%3D&ch=0&cr=3&dr=0&lr=all&cd=0%7C0%7C0%7C&cv=1&br=562&bt=281&cs=0&ds=6&ft=4fUEKMT88Zmo0AJNjb4jVovrrpWrKsd.&mime_type=video_mp4&qs=0&rc=OzdpZzdoO2Q1NWZlNjw6O0BpanZzNm85cmlmdzMzZjczM0A1YTFgLjQwXy8xL15gLmEtYSMyNDRyMmRjXjJgLS1kMWNzcw%3D%3D&btag=e00090000&expire=1733181993&l=20241130232444DAC94285ABBC8AD03578&ply_type=2&policy=2&signature=a65f4b6149b758d958607dd48e2d0477&tk=tt_chain_token",
            "https://www.tiktok.com/aweme/v1/play/?faid=1988&file_id=08d719c3ab2c4222ba387e14cd4fd488&is_play_url=1&item_id=7442978238504127777&line=0&ply_type=2&redirect=0&signaturev3=dmlkZW9faWQ7ZmlsZV9pZDtpdGVtX2lkLjFmN2M3OTMyMDI4OWJhMDRhMTJjMGQ5ZmQyNzkxNjgx&tk=tt_chain_token&vidc=useast2a&video_id=v0f044gc0000ct5caffog65lu37p7s5g"
          ],
          "Width": 576
        },
        "QualityType": 20
      },
      {
        "Bitrate": 258187,
        "CodecType": "h265_hvc1",
        "GearName": "adapt_lowest_1080_1",
        "MVMAF": "\"{\\\"v2.0\\\": {\\\"srv1\\\": {\\\"v1080\\\": -1, \\\"v960\\\": -1, \\\"v864\\\": -1, \\\"v720\\\": -1}, \\\"ori\\\": {\\\"v1080\\\": 95.368, \\\"v960\\\": 94.787, \\\"v864\\\": 95.39, \\\"v720\\\": 96.139}}}\"",
        "PlayAddr": {
          "DataSize": 3473648,
          "FileCs": "c:0-91786-0247",
          "FileHash": "f63ec4e5785f8257b0dacb16f3421f7f",
          "Height": 1920,
          "Uri": "v0f044gc0000ct5caffog65lu37p7s5g",
          "UrlKey": "v0f044gc0000ct5caffog65lu37p7s5g_bytevc1_1080p_258187",
          "UrlList": [
            "https://v16-webapp-prime.tiktok.com/video/tos/useast2a/tos-useast2a-ve-0068-euttp/oEBRDEQeI4nQTMEnEBKU8PFDZSLxxDfsr2AyU9/?a=1988&bti=NDU3ZjAwOg%3D%3D&ch=0&cr=3&dr=0&lr=all&cd=0%7C0%7C0%7C&cv=1&br=504&bt=252&cs=2&ds=4&eid=256&ft=4fUEKMT88Zmo0AJNjb4jVovrrpWrKsd.&mime_type=video_mp4&qs=15&rc=OmkzaDdnNDRlZDVlZzw1ZkBpanZzNm85cmlmdzMzZjczM0BeXzFiMjQzXmAxLi5eMmI1YSMyNDRyMmRjXjJgLS1kMWNzcw%3D%3D&btag=e00090000&expire=1733181993&l=20241130232444DAC94285ABBC8AD03578&ply_type=2&policy=2&signature=a7c428be70bb6234c41ab64bc6e90931&tk=tt_chain_token",
            "https://v19-webapp-prime.tiktok.com/video/tos/useast2a/tos-useast2a-ve-0068-euttp/oEBRDEQeI4nQTMEnEBKU8PFDZSLxxDfsr2AyU9/?a=1988&bti=NDU3ZjAwOg%3D%3D&ch=0&cr=3&dr=0&lr=all&cd=0%7C0%7C0%7C&cv=1&br=504&bt=252&cs=2&ds=4&eid=256&ft=4fUEKMT88Zmo0AJNjb4jVovrrpWrKsd.&mime_type=video_mp4&qs=15&rc=OmkzaDdnNDRlZDVlZzw1ZkBpanZzNm85cmlmdzMzZjczM0BeXzFiMjQzXmAxLi5eMmI1YSMyNDRyMmRjXjJgLS1kMWNzcw%3D%3D&btag=e00090000&expire=1733181993&l=20241130232444DAC94285ABBC8AD03578&ply_type=2&policy=2&signature=a7c428be70bb6234c41ab64bc6e90931&tk=tt_chain_token",
            "https://www.tiktok.com/aweme/v1/play/?faid=1988&file_id=8ce259ad1b124acba1617d54ee40bfa7&is_play_url=1&item_id=7442978238504127777&line=0&ply_type=2&redirect=0&signaturev3=dmlkZW9faWQ7ZmlsZV9pZDtpdGVtX2lkLjBiMjM1MjRhNDhjMDk4Nzc3MzRkMGQ0Mzg0YzE5Mzlk&tk=tt_chain_token&vidc=useast2a&video_id=v0f044gc0000ct5caffog65lu37p7s5g"
          ],
          "Width": 1080
        },
        "QualityType": 2
      },
      {
        "Bitrate": 184988,
        "CodecType": "h265_hvc1",
        "GearName": "adapt_lower_720_1",
        "MVMAF": "\"{\\\"v2.0\\\": {\\\"srv1\\\": {\\\"v1080\\\": 98.111, \\\"v960\\\": 98.948, \\\"v864\\\": 99.172, \\\"v720\\\": 99.787}, \\\"ori\\\": {\\\"v1080\\\": 89.621, \\\"v960\\\": 92.559, \\\"v864\\\": 93.67, \\\"v720\\\": 96.622}}}\"",
        "PlayAddr": {
          "DataSize": 2489647,
          "FileCs": "c:0-90265-8489",
          "FileHash": "5110c75e43b757b5348a3f1b93fc9179",
          "Height": 1280,
          "Uri": "v0f044gc0000ct5caffog65lu37p7s5g",
          "UrlKey": "v0f044gc0000ct5caffog65lu37p7s5g_bytevc1_720p_184988",
          "UrlList": [
            "https://v16-webapp-prime.tiktok.com/video/tos/useast2a/tos-useast2a-ve-0068c001-euttp/oIUSDfr9EEMPEsx84QnQFBZKIDRsAXTL9DlCea/?a=1988&bti=NDU3ZjAwOg%3D%3D&ch=0&cr=3&dr=0&lr=all&cd=0%7C0%7C0%7C&cv=1&br=360&bt=180&cs=2&ds=3&eid=256&ft=4fUEKMT88Zmo0AJNjb4jVovrrpWrKsd.&mime_type=video_mp4&qs=14&rc=MzNmNTc8MzNlMzM1NDhmOkBpanZzNm85cmlmdzMzZjczM0BfMC41YmEzXjIxXy8wNjUvYSMyNDRyMmRjXjJgLS1kMWNzcw%3D%3D&btag=e00090000&expire=1733181993&l=20241130232444DAC94285ABBC8AD03578&ply_type=2&policy=2&signature=3a559fa3f3cb938c45b4ec93f1e39686&tk=tt_chain_token",
            "https://v19-webapp-prime.tiktok.com/video/tos/useast2a/tos-useast2a-ve-0068c001-euttp/oIUSDfr9EEMPEsx84QnQFBZKIDRsAXTL9DlCea/?a=1988&bti=NDU3ZjAwOg%3D%3D&ch=0&cr=3&dr=0&lr=all&cd=0%7C0%7C0%7C&cv=1&br=360&bt=180&cs=2&ds=3&eid=256&ft=4fUEKMT88Zmo0AJNjb4jVovrrpWrKsd.&mime_type=video_mp4&qs=14&rc=MzNmNTc8MzNlMzM1NDhmOkBpanZzNm85cmlmdzMzZjczM0BfMC41YmEzXjIxXy8wNjUvYSMyNDRyMmRjXjJgLS1kMWNzcw%3D%3D&btag=e00090000&expire=1733181993&l=20241130232444DAC94285ABBC8AD03578&ply_type=2&policy=2&signature=3a559fa3f3cb938c45b4ec93f1e39686&tk=tt_chain_token",
            "https://www.tiktok.com/aweme/v1/play/?faid=1988&file_id=278c953122b0405ba060d9e4821c30b0&is_play_url=1&item_id=7442978238504127777&line=0&ply_type=2&redirect=0&signaturev3=dmlkZW9faWQ7ZmlsZV9pZDtpdGVtX2lkLmE0Njg0ODNlMDQyYWY4OWYxNGI0MTE3ZGFlZWYwOTJl&tk=tt_chain_token&vidc=useast2a&video_id=v0f044gc0000ct5caffog65lu37p7s5g"
          ],
          "Width": 720
        },
        "QualityType": 14
      },
      {
        "Bitrate": 179580,
        "CodecType": "h264",
        "GearName": "lower_540_0",
        "MVMAF": "\"{\\\"v2.0\\\": {\\\"srv1\\\": {\\\"v1080\\\": 90.826, \\\"v960\\\": 93.837, \\\"v864\\\": 97.086, \\\"v720\\\": 98.187}, \\\"ori\\\": {\\\"v1080\\\": 78.54, \\\"v960\\\": 84.148, \\\"v864\\\": 87.654, \\\"v720\\\": 89.773}}}\"",
        "PlayAddr": {
          "DataSize": 2416860,
          "FileCs": "c:0-89829-66f2",
          "FileHash": "9363842a366a260d06213eed1e1d8c11",
          "Height": 1024,
          "Uri": "v0f044gc0000ct5caffog65lu37p7s5g",
          "UrlKey": "v0f044gc0000ct5caffog65lu37p7s5g_h264_540p_179580",
          "UrlList": [
            "https://v16-webapp-prime.tiktok.com/video/tos/useast2a/tos-useast2a-ve-0068-euttp/oEATDEYnPE9QCRXEULKfBFxShDAY4sIr8cTeZQ/?a=1988&bti=NDU3ZjAwOg%3D%3D&ch=0&cr=3&dr=0&lr=all&cd=0%7C0%7C0%7C&cv=1&br=350&bt=175&cs=0&ds=6&ft=4fUEKMT88Zmo0AJNjb4jVovrrpWrKsd.&mime_type=video_mp4&qs=4&rc=OjY5OzY3PDxoZWlnNmU3NkBpanZzNm85cmlmdzMzZjczM0BjLjNfMzVeXy0xY2MtMzQyYSMyNDRyMmRjXjJgLS1kMWNzcw%3D%3D&btag=e00090000&expire=1733181993&l=20241130232444DAC94285ABBC8AD03578&ply_type=2&policy=2&signature=4c98d5601b55f39342927b9fe13859bd&tk=tt_chain_token",
            "https://v19-webapp-prime.tiktok.com/video/tos/useast2a/tos-useast2a-ve-0068-euttp/oEATDEYnPE9QCRXEULKfBFxShDAY4sIr8cTeZQ/?a=1988&bti=NDU3ZjAwOg%3D%3D&ch=0&cr=3&dr=0&lr=all&cd=0%7C0%7C0%7C&cv=1&br=350&bt=175&cs=0&ds=6&ft=4fUEKMT88Zmo0AJNjb4jVovrrpWrKsd.&mime_type=video_mp4&qs=4&rc=OjY5OzY3PDxoZWlnNmU3NkBpanZzNm85cmlmdzMzZjczM0BjLjNfMzVeXy0xY2MtMzQyYSMyNDRyMmRjXjJgLS1kMWNzcw%3D%3D&btag=e00090000&expire=1733181993&l=20241130232444DAC94285ABBC8AD03578&ply_type=2&policy=2&signature=4c98d5601b55f39342927b9fe13859bd&tk=tt_chain_token",
            "https://www.tiktok.com/aweme/v1/play/?faid=1988&file_id=53746b03fdff4b0eb9a98463b86613f7&is_play_url=1&item_id=7442978238504127777&line=0&ply_type=2&redirect=0&signaturev3=dmlkZW9faWQ7ZmlsZV9pZDtpdGVtX2lkLmU0YmE0MzJlOWVhZDI4MTYwYWIyNzBhZDM1OGQ0NjUx&tk=tt_chain_token&vidc=useast2a&video_id=v0f044gc0000ct5caffog65lu37p7s5g"
          ],
          "Width": 576
        },
        "QualityType": 24
      },
      {
        "Bitrate": 144279,
        "CodecType": "h265_hvc1",
        "GearName": "adapt_540_1",
        "MVMAF": "\"{\\\"v2.0\\\": {\\\"srv1\\\": {\\\"v1080\\\": 96.318, \\\"v960\\\": 96.993, \\\"v864\\\": 98.991, \\\"v720\\\": 99.818}, \\\"ori\\\": {\\\"v1080\\\": 85.021, \\\"v960\\\": 88.502, \\\"v864\\\": 90.361, \\\"v720\\\": 93.168}}}\"",
        "PlayAddr": {
          "DataSize": 1941764,
          "FileCs": "c:0-90265-1fdc",
          "FileHash": "9ff1ee4322923e8b33504413d04358de",
          "Height": 1024,
          "Uri": "v0f044gc0000ct5caffog65lu37p7s5g",
          "UrlKey": "v0f044gc0000ct5caffog65lu37p7s5g_bytevc1_540p_144279",
          "UrlList": [
            "https://v16-webapp-prime.tiktok.com/video/tos/useast2a/tos-useast2a-ve-0068c001-euttp/o8CDUQDfFD49SjVutRpWABnE4r8QIPgfQnsZFE/?a=1988&bti=NDU3ZjAwOg%3D%3D&ch=0&cr=3&dr=0&lr=all&cd=0%7C0%7C0%7C&cv=1&br=280&bt=140&cs=2&ds=6&eid=256&ft=4fUEKMT88Zmo0AJNjb4jVovrrpWrKsd.&mime_type=video_mp4&qs=11&rc=NTVpM2lnNDw1Nzk7NztlaEBpanZzNm85cmlmdzMzZjczM0BeNTJhMC8vNS4xMmEwMWMxYSMyNDRyMmRjXjJgLS1kMWNzcw%3D%3D&btag=e00090000&expire=1733181993&l=20241130232444DAC94285ABBC8AD03578&ply_type=2&policy=2&signature=dc3fb82de0759e45f7e1350e77f9dded&tk=tt_chain_token",
            "https://v19-webapp-prime.tiktok.com/video/tos/useast2a/tos-useast2a-ve-0068c001-euttp/o8CDUQDfFD49SjVutRpWABnE4r8QIPgfQnsZFE/?a=1988&bti=NDU3ZjAwOg%3D%3D&ch=0&cr=3&dr=0&lr=all&cd=0%7C0%7C0%7C&cv=1&br=280&bt=140&cs=2&ds=6&eid=256&ft=4fUEKMT88Zmo0AJNjb4jVovrrpWrKsd.&mime_type=video_mp4&qs=11&rc=NTVpM2lnNDw1Nzk7NztlaEBpanZzNm85cmlmdzMzZjczM0BeNTJhMC8vNS4xMmEwMWMxYSMyNDRyMmRjXjJgLS1kMWNzcw%3D%3D&btag=e00090000&expire=1733181993&l=20241130232444DAC94285ABBC8AD03578&ply_type=2&policy=2&signature=dc3fb82de0759e45f7e1350e77f9dded&tk=tt_chain_token",
            "https://www.tiktok.com/aweme/v1/play/?faid=1988&file_id=4efb4834d856441289212d3fd05f82a2&is_play_url=1&item_id=7442978238504127777&line=0&ply_type=2&redirect=0&signaturev3=dmlkZW9faWQ7ZmlsZV9pZDtpdGVtX2lkLjg1ZGI4ODMwMWI5ODUwYjliYTU0NzM4MGM4MmE3ZTdj&tk=tt_chain_token&vidc=useast2a&video_id=v0f044gc0000ct5caffog65lu37p7s5g"
          ],
          "Width": 576
        },
        "QualityType": 28
      }
    ],
    "claInfo": {
      "captionInfos": [
        {
          "captionFormat": "webvtt",
          "claSubtitleID": "7442978821315250977",
          "expire": "1733181993",
          "isAutoGen": true,
          "isOriginalCaption": true,
          "language": "ron-RO",
          "languageCode": "",
          "languageID": "40",
          "subID": "-1947092366",
          "subtitleType": "1",
          "url": "https://v16-webapp.tiktok.com/d93fad1f6e7a487914b8c5362ebaf068/674e4229/video/tos/useast2a/tos-useast2a-v-0037-euttp/17b4ae28750f4f1eb69c3e178693037c/?a=1988&bti=NDU3ZjAwOg%3D%3D&ch=0&cr=3&dr=0&lr=all&cd=0%7C0%7C0%7C&cv=1&br=12026&bt=6013&ds=4&ft=4b~OyMT88Zmo0AJNjb4jVovrrpWrKsd.&mime_type=video_mp4&qs=13&rc=anZzNm85cmlmdzMzZjczM0BpanZzNm85cmlmdzMzZjczM0AyNDRyMmRjXjJgLS1kMWNzYSMyNDRyMmRjXjJgLS1kMWNzcw%3D%3D&l=20241130232444DAC94285ABBC8AD03578&btag=e00050000",
          "urlList": [
            "https://v16-webapp.tiktok.com/d93fad1f6e7a487914b8c5362ebaf068/674e4229/video/tos/useast2a/tos-useast2a-v-0037-euttp/17b4ae28750f4f1eb69c3e178693037c/?a=1988&bti=NDU3ZjAwOg%3D%3D&ch=0&cr=3&dr=0&lr=all&cd=0%7C0%7C0%7C&cv=1&br=12026&bt=6013&ds=4&ft=4b~OyMT88Zmo0AJNjb4jVovrrpWrKsd.&mime_type=video_mp4&qs=13&rc=anZzNm85cmlmdzMzZjczM0BpanZzNm85cmlmdzMzZjczM0AyNDRyMmRjXjJgLS1kMWNzYSMyNDRyMmRjXjJgLS1kMWNzcw%3D%3D&l=20241130232444DAC94285ABBC8AD03578&btag=e00050000",
            "https://v16-webapp.tiktok.com/d93fad1f6e7a487914b8c5362ebaf068/674e4229/video/tos/useast2a/tos-useast2a-v-0037-euttp/17b4ae28750f4f1eb69c3e178693037c/?a=1988&bti=NDU3ZjAwOg%3D%3D&ch=0&cr=3&dr=0&lr=all&cd=0%7C0%7C0%7C&cv=1&br=12026&bt=6013&ds=4&ft=4b~OyMT88Zmo0AJNjb4jVovrrpWrKsd.&mime_type=video_mp4&qs=13&rc=anZzNm85cmlmdzMzZjczM0BpanZzNm85cmlmdzMzZjczM0AyNDRyMmRjXjJgLS1kMWNzYSMyNDRyMmRjXjJgLS1kMWNzcw%3D%3D&l=20241130232444DAC94285ABBC8AD03578&btag=e00050000",
            "https://vas-useast2a.tiktokv.com/tiktok/v1/subtitle/url?aid=1988&format=webvtt&language=ron-RO&sign=ab472bf30dd8b2b0cc95fdc2f571e185&version=1%3Awhisper_lid&vid=v0f044gc0000ct5caffog65lu37p7s5g"
          ],
          "variant": "whisper_lid"
        }
      ],
      "captionsType": 1,
      "enableAutoCaption": true,
      "hasOriginalAudio": true,
      "originalLanguageInfo": {
        "language": "ron-RO",
        "languageCode": "",
        "languageID": "40"
      }
    },
    "codecType": "h264",
    "cover": "https://p16-sign-useast2a.tiktokcdn.com/obj/tos-useast2a-p-0037-euttp/ocbgwPIgQGgO7ilezFLereEPsap5eIAwGEYjEX?lk3s=b59d6b55&x-expires=1733180400&x-signature=lDT6m2KmUH5c5FWn5PXtw9SkUQc%3D&shp=b59d6b55&shcp=-",
    "definition": "540p",
    "downloadAddr": "https://v16-webapp-prime.tiktok.com/video/tos/useast2a/tos-useast2a-ve-0068-euttp/okJDUYDyFE89SxKHHRtLABTE4reIEPQfQnsZRE/?a=1988&bti=NDU3ZjAwOg%3D%3D&ch=0&cr=3&dr=0&lr=all&cd=0%7C0%7C0%7C&cv=1&br=624&bt=312&cs=0&ds=3&ft=4fUEKMT88Zmo0AJNjb4jVovrrpWrKsd.&mime_type=video_mp4&qs=0&rc=NztlZDg1ZjZoOWQ8aDVlO0BpanZzNm85cmlmdzMzZjczM0BeYDRgMjBfNjYxMTY2MjVhYSMyNDRyMmRjXjJgLS1kMWNzcw%3D%3D&btag=e00090000&expire=1733181993&l=20241130232444DAC94285ABBC8AD03578&ply_type=2&policy=2&signature=32318ff6b4432c0cc79c5aa0dc83bdb4&tk=tt_chain_token",
    "duration": 107,
    "dynamicCover": "https://p16-sign-useast2a.tiktokcdn.com/obj/tos-useast2a-p-0037-euttp/oc4IXV8ZDDxSePTKCLFZQUIERArIBR9fEcBn9s?lk3s=b59d6b55&x-expires=1733180400&x-signature=NHxSpVd2I5ACfXb0nlqOKVbEhok%3D&shp=b59d6b55&shcp=-",
    "encodeUserTag": "",
    "encodedType": "normal",
    "format": "mp4",
    "height": 1024,
    "id": "7442978238504127777",
    "originCover": "https://p16-sign-useast2a.tiktokcdn.com/obj/tos-useast2a-p-0037-euttp/ossEZSA14FTLABPUenr9RTQ7UEIgfD8DIKxXJd?lk3s=b59d6b55&x-expires=1733180400&x-signature=t9WtTrQ8XRJycSKtxjomGnt89JI%3D&shp=b59d6b55&shcp=-",
    "playAddr": "https://v16-webapp-prime.tiktok.com/video/tos/useast2a/tos-useast2a-ve-0068c001-euttp/oEYELfsKTQcRDVDEQerEA9BPxDSFI7dZn8U4tB/?a=1988&bti=NDU3ZjAwOg%3D%3D&ch=0&cr=3&dr=0&lr=all&cd=0%7C0%7C0%7C&cv=1&br=562&bt=281&cs=0&ds=6&ft=4fUEKMT88Zmo0AJNjb4jVovrrpWrKsd.&mime_type=video_mp4&qs=0&rc=OzdpZzdoO2Q1NWZlNjw6O0BpanZzNm85cmlmdzMzZjczM0A1YTFgLjQwXy8xL15gLmEtYSMyNDRyMmRjXjJgLS1kMWNzcw%3D%3D&btag=e00090000&expire=1733181993&l=20241130232444DAC94285ABBC8AD03578&ply_type=2&policy=2&signature=a65f4b6149b758d958607dd48e2d0477&tk=tt_chain_token",
    "ratio": "540p",
    "reflowCover": "https://p16-sign-useast2a.tiktokcdn.com/tos-useast2a-p-0037-euttp/ocbgwPIgQGgO7ilezFLereEPsap5eIAwGEYjEX~tplv-photomode-video-cover:480:480.jpeg?lk3s=b59d6b55&x-expires=1733180400&x-signature=FzVX8xO7ZTyxRC6pp5Wb47MoA9A%3D&shp=b59d6b55&shcp=-",
    "shareCover": [
      "",
      "https://p16-sign-useast2a.tiktokcdn.com/tos-useast2a-p-0037-euttp/ossEZSA14FTLABPUenr9RTQ7UEIgfD8DIKxXJd~tplv-photomode-tiktok-play.jpeg?lk3s=b59d6b55&x-expires=1733612400&x-signature=8oJneALAVxcXWQmD08H%2FOHUnNAM%3D&shp=b59d6b55&shcp=-",
      "https://p16-sign-useast2a.tiktokcdn.com/tos-useast2a-p-0037-euttp/ossEZSA14FTLABPUenr9RTQ7UEIgfD8DIKxXJd~tplv-photomode-share-play.jpeg?lk3s=b59d6b55&x-expires=1733612400&x-signature=gfua%2BqlP72rtcUF4LL0He9j5bVI%3D&shp=b59d6b55&shcp=-"
    ],
    "size": 3883566,
    "subtitleInfos": [
      {
        "Format": "webvtt",
        "LanguageCodeName": "ron-RO",
        "LanguageID": "40",
        "Size": 2360,
        "Source": "ASR",
        "Url": "https://v16-webapp.tiktok.com/d93fad1f6e7a487914b8c5362ebaf068/674e4229/video/tos/useast2a/tos-useast2a-v-0037-euttp/17b4ae28750f4f1eb69c3e178693037c/?a=1988&bti=NDU3ZjAwOg%3D%3D&ch=0&cr=3&dr=0&lr=all&cd=0%7C0%7C0%7C&cv=1&br=12026&bt=6013&ds=4&ft=4b~OyMT88Zmo0AJNjb4jVovrrpWrKsd.&mime_type=video_mp4&qs=13&rc=anZzNm85cmlmdzMzZjczM0BpanZzNm85cmlmdzMzZjczM0AyNDRyMmRjXjJgLS1kMWNzYSMyNDRyMmRjXjJgLS1kMWNzcw%3D%3D&l=20241130232444DAC94285ABBC8AD03578&btag=e00050000",
        "UrlExpire": 1733181993,
        "Version": "1:whisper_lid",
        "VideoSubtitleID": -1947092366
      }
    ],
    "videoQuality": "normal",
    "volumeInfo": {
      "Loudness": -15.9,
      "Peak": 1
    },
    "width": 576,
    "zoomCover": {
      "240": "https://p16-sign-useast2a.tiktokcdn.com/tos-useast2a-p-0037-euttp/ocbgwPIgQGgO7ilezFLereEPsap5eIAwGEYjEX~tplv-photomode-zoomcover:240:240.jpeg?lk3s=b59d6b55&x-expires=1733180400&x-signature=E6l2WoKvaoiyO77uaAFbX1kzwDs%3D&shp=b59d6b55&shcp=-",
      "480": "https://p16-sign-useast2a.tiktokcdn.com/tos-useast2a-p-0037-euttp/ocbgwPIgQGgO7ilezFLereEPsap5eIAwGEYjEX~tplv-photomode-zoomcover:480:480.jpeg?lk3s=b59d6b55&x-expires=1733180400&x-signature=HDM7XVI2%2FLrEFsyceoENRh5qr0E%3D&shp=b59d6b55&shcp=-",
      "720": "https://p16-sign-useast2a.tiktokcdn.com/tos-useast2a-p-0037-euttp/ocbgwPIgQGgO7ilezFLereEPsap5eIAwGEYjEX~tplv-photomode-zoomcover:720:720.jpeg?lk3s=b59d6b55&x-expires=1733180400&x-signature=1WdGVHep%2FVRLuq%2B6BOPTsXPYmfk%3D&shp=b59d6b55&shcp=-",
      "960": "https://p16-sign-useast2a.tiktokcdn.com/tos-useast2a-p-0037-euttp/ocbgwPIgQGgO7ilezFLereEPsap5eIAwGEYjEX~tplv-photomode-zoomcover:960:960.jpeg?lk3s=b59d6b55&x-expires=1733180400&x-signature=wqRW33TaHiMEHV6Nj4Ym6QzKZRY%3D&shp=b59d6b55&shcp=-"
    }
  },
  "vl1": false,
  "comments": [
    {
      "author_pin": false,
      "aweme_id": "7442978238504127777",
      "cid": "7442987353181291296",
      "collect_stat": 0,
      "comment_language": "ro",
      "comment_post_item_ids": null,
      "create_time": 1732955574,
      "digg_count": 879,
      "forbid_reply_with_video": true,
      "image_list": null,
      "is_author_digged": true,
      "is_comment_translatable": true,
      "label_list": [
        {
          "text": "Liked by creator",
          "type": 20
        }
      ],
      "no_show": false,
      "reply_comment": null,
      "reply_comment_total": 41,
      "reply_id": "0",
      "reply_to_reply_id": "0",
      "share_info": {
        "acl": {
          "code": 0,
          "extra": "{}"
        },
        "desc": "Deniza38’s comment: domnul președinte Calin Georgescu cînd vorbește îți dă niste emoții care nu le-am trăit niciodată mă face să plâng doamne ajuta Calin Georgescu președinte 🙏🙏",
        "title": "#2018 #goviral #viral #romaniaviral #foryou #fypage #foryoupage ",
        "url": "https://m.tiktok.com/v/7442978238504127777.html?_d=49jjef66j4ca6g&comment_author_id=6832759984624354310&preview_pb=0&share_comment_id=7442987353181291296&share_item_id=7442978238504127777&sharer_language=en-US&source=h5_m&u_code=e8hegggb201lba"
      },
      "sort_extra_score": {
        "reply_score": 0.003014,
        "show_more_score": 0.018165
      },
      "sort_tags": "{\"author_digg\":1,\"top_list\":1}",
      "status": 1,
      "stick_position": 0,
      "text": "domnul președinte Calin Georgescu cînd vorbește îți dă niste emoții care nu le-am trăit niciodată mă face să plâng doamne ajuta Calin Georgescu președinte 🙏🙏",
      "text_extra": [],
      "trans_btn_style": 1,
      "user": {
        "account_labels": null,
        "ad_cover_url": null,
        "advance_feature_item_order": null,
        "advanced_feature_info": null,
        "avatar_thumb": {
          "uri": "tos-useast2a-avt-0068-euttp/ef146e55fc083a4e331d1db53b109270",
          "url_list": [
            "https://p16-sign-useast2a.tiktokcdn.com/tos-useast2a-avt-0068-euttp/ef146e55fc083a4e331d1db53b109270~c5_100x100.jpg?lk3s=30310797&nonce=32296&refresh_token=edfa506f0504da83ee809b7b55d3b449&x-expires=1733094000&x-signature=d8kDY1ptpXXc8hedvGRzOcNZevQ%3D&shp=30310797&shcp=-",
            "https://p16-sign-useast2a.tiktokcdn.com/tos-useast2a-avt-0068-euttp/ef146e55fc083a4e331d1db53b109270~c5_100x100.jpeg?lk3s=30310797&nonce=96424&refresh_token=022024f5c86aaa9df170e61118762a75&x-expires=1733094000&x-signature=Mhm8yIAuD6YYxtjC6tdxqrbdZZg%3D&shp=30310797&shcp=-"
          ],
          "url_prefix": null
        },
        "bold_fields": null,
        "can_message_follow_status_list": null,
        "can_set_geofencing": null,
        "cha_list": null,
        "cover_url": null,
        "custom_verify": "",
        "enterprise_verify_reason": "",
        "events": null,
        "followers_detail": null,
        "geofencing": null,
        "homepage_bottom_toast": null,
        "item_list": null,
        "mutual_relation_avatars": null,
        "need_points": null,
        "nickname": "Deniza38",
        "platform_sync_info": null,
        "relative_users": null,
        "search_highlight": null,
        "sec_uid": "MS4wLjABAAAAwCDsoNbDg9PklSPRvcDGCk4COrx8npWNRbfIh2SV19C-K5R10iiilhCNiHMwi0uK",
        "shield_edit_field_info": null,
        "type_label": null,
        "uid": "6832759984624354310",
        "unique_id": "denizkay38831",
        "user_profile_guide": null,
        "user_tags": null,
        "white_cover_url": null
      },
      "user_buried": false,
      "user_digged": 0
    },
    {
      "author_pin": false,
      "aweme_id": "7442978238504127777",
      "cid": "7442984547643294496",
      "collect_stat": 0,
      "comment_language": "ro",
      "comment_post_item_ids": null,
      "create_time": 1732954903,
      "digg_count": 1024,
      "forbid_reply_with_video": true,
      "image_list": null,
      "is_author_digged": true,
      "is_comment_translatable": true,
      "label_list": [
        {
          "text": "Liked by creator",
          "type": 20
        }
      ],
      "no_show": false,
      "reply_comment": null,
      "reply_comment_total": 12,
      "reply_id": "0",
      "reply_to_reply_id": "0",
      "share_info": {
        "acl": {
          "code": 0,
          "extra": "{}"
        },
        "desc": "D𝓮𝓷𝓲𝓼𝓪👑’s comment: Președintele Meu te ador Din inima ❤️🥰🙏🙏🙏",
        "title": "#2018 #goviral #viral #romaniaviral #foryou #fypage #foryoupage ",
        "url": "https://m.tiktok.com/v/7442978238504127777.html?_d=49jjef66j4ca6g&comment_author_id=6654046569707782149&preview_pb=0&share_comment_id=7442984547643294496&share_item_id=7442978238504127777&sharer_language=en-US&source=h5_m&u_code=e8hegggb201lba"
      },
      "sort_extra_score": {
        "reply_score": 0.00054,
        "show_more_score": 0.019744
      },
      "sort_tags": "{\"author_digg\":1,\"top_list\":1}",
      "status": 1,
      "stick_position": 0,
      "text": "Președintele Meu te ador Din inima ❤️🥰🙏🙏🙏",
      "text_extra": [],
      "trans_btn_style": 1,
      "user": {
        "account_labels": null,
        "ad_cover_url": null,
        "advance_feature_item_order": null,
        "advanced_feature_info": null,
        "avatar_thumb": {
          "uri": "tos-useast2a-avt-0068-euttp/c361a5f441824d99b1caf65f2ff48cf4",
          "url_list": [
            "https://p16-sign-useast2a.tiktokcdn.com/tos-useast2a-avt-0068-euttp/c361a5f441824d99b1caf65f2ff48cf4~c5_100x100.jpg?lk3s=30310797&nonce=40004&refresh_token=51ee1ad840b0cb3fd6e527f4af218a0a&x-expires=1733094000&x-signature=v1Toz501j%2Fnxym%2FKC%2Fk5hDsSQes%3D&shp=30310797&shcp=-",
            "https://p16-sign-useast2a.tiktokcdn.com/tos-useast2a-avt-0068-euttp/c361a5f441824d99b1caf65f2ff48cf4~c5_100x100.jpeg?lk3s=30310797&nonce=64221&refresh_token=a47d711cd61670855bad8cc44a42cede&x-expires=1733094000&x-signature=RR%2BSgFJgk5sm0xp9YnAplOa9474%3D&shp=30310797&shcp=-"
          ],
          "url_prefix": null
        },
        "bold_fields": null,
        "can_message_follow_status_list": null,
        "can_set_geofencing": null,
        "cha_list": null,
        "cover_url": null,
        "custom_verify": "",
        "enterprise_verify_reason": "",
        "events": null,
        "followers_detail": null,
        "geofencing": null,
        "homepage_bottom_toast": null,
        "item_list": null,
        "mutual_relation_avatars": null,
        "need_points": null,
        "nickname": "D𝓮𝓷𝓲𝓼𝓪👑",
        "platform_sync_info": null,
        "relative_users": null,
        "search_highlight": null,
        "sec_uid": "MS4wLjABAAAAVgWwWNWKPIXdNx7Vp1qj3bGn1_HVS9t3yBpxmpVnCSHih7RbnzAvPBjTkVv0UufU",
        "shield_edit_field_info": null,
        "type_label": null,
        "uid": "6654046569707782149",
        "unique_id": "denisa_farcas98",
        "user_profile_guide": null,
        "user_tags": null,
        "white_cover_url": null
      },
      "user_buried": false,
      "user_digged": 0
    },
    {
      "author_pin": false,
      "aweme_id": "7442978238504127777",
      "cid": "7443013010124751649",
      "collect_stat": 0,
      "comment_language": "ro",
      "comment_post_item_ids": null,
      "create_time": 1732961562,
      "digg_count": 96,
      "forbid_reply_with_video": true,
      "image_list": null,
      "is_author_digged": false,
      "is_comment_translatable": true,
      "label_list": null,
      "no_show": false,
      "reply_comment": null,
      "reply_comment_total": 1,
      "reply_id": "0",
      "reply_to_reply_id": "0",
      "share_info": {
        "acl": {
          "code": 0,
          "extra": "{}"
        },
        "desc": "lilipiron1392’s comment: SĂ NU NE DEZAMĂGIȚI\nV-am ales cu lacrimi și cu speranța că o să aveți milă de acest popor greu încercat de 34 de ani.",
        "title": "#2018 #goviral #viral #romaniaviral #foryou #fypage #foryoupage ",
        "url": "https://m.tiktok.com/v/7442978238504127777.html?_d=49jjef66j4ca6g&comment_author_id=6812301584299525125&preview_pb=0&share_comment_id=7443013010124751649&share_item_id=7442978238504127777&sharer_language=en-US&source=h5_m&u_code=e8hegggb201lba"
      },
      "sort_extra_score": {
        "reply_score": 0.000695,
        "show_more_score": 0.030399
      },
      "sort_tags": "{\"top_list\":1}",
      "status": 1,
      "stick_position": 0,
      "text": "SĂ NU NE DEZAMĂGIȚI\nV-am ales cu lacrimi și cu speranța că o să aveți milă de acest popor greu încercat de 34 de ani.",
      "text_extra": [],
      "trans_btn_style": 1,
      "user": {
        "account_labels": null,
        "ad_cover_url": null,
        "advance_feature_item_order": null,
        "advanced_feature_info": null,
        "avatar_thumb": {
          "uri": "tos-maliva-avt-0068/7333895108410933254",
          "url_list": [
            "https://p16-sign-va.tiktokcdn.com/tos-maliva-avt-0068/7333895108410933254~c5_100x100.jpg?lk3s=30310797&nonce=75177&refresh_token=c69477dbc25d71c39fbfeeb6c0034c55&x-expires=1733094000&x-signature=ySYl8jTQ0V55OQ4BQdZQYbI9rwc%3D&shp=30310797&shcp=-",
            "https://p16-sign-va.tiktokcdn.com/tos-maliva-avt-0068/7333895108410933254~c5_100x100.jpeg?lk3s=30310797&nonce=56950&refresh_token=bc60e8ab93129fa3e633ad1dea45b681&x-expires=1733094000&x-signature=JCqxpjmrMnDNtRT6E0qA5%2Fm1SNc%3D&shp=30310797&shcp=-"
          ],
          "url_prefix": null
        },
        "bold_fields": null,
        "can_message_follow_status_list": null,
        "can_set_geofencing": null,
        "cha_list": null,
        "cover_url": null,
        "custom_verify": "",
        "enterprise_verify_reason": "",
        "events": null,
        "followers_detail": null,
        "geofencing": null,
        "homepage_bottom_toast": null,
        "item_list": null,
        "mutual_relation_avatars": null,
        "need_points": null,
        "nickname": "lilipiron1392",
        "platform_sync_info": null,
        "relative_users": null,
        "search_highlight": null,
        "sec_uid": "MS4wLjABAAAA2DDqF9Ixwq8lhF_32t1KTP82nhYmtas-vNRXQfIKKM8k0j7ktcOtTvB2OsUWlppR",
        "shield_edit_field_info": null,
        "type_label": null,
        "uid": "6812301584299525125",
        "unique_id": "lilipiron1392",
        "user_profile_guide": null,
        "user_tags": null,
        "white_cover_url": null
      },
      "user_buried": false,
      "user_digged": 0
    },
    {
      "author_pin": false,
      "aweme_id": "7442978238504127777",
      "cid": "7443020462462550817",
      "collect_stat": 0,
      "comment_language": "ro",
      "comment_post_item_ids": null,
      "create_time": 1732963296,
      "digg_count": 532,
      "forbid_reply_with_video": true,
      "image_list": null,
      "is_author_digged": true,
      "is_comment_translatable": true,
      "label_list": [
        {
          "text": "Liked by creator",
          "type": 20
        }
      ],
      "no_show": false,
      "reply_comment": null,
      "reply_comment_total": 2,
      "reply_id": "0",
      "reply_to_reply_id": "0",
      "share_info": {
        "acl": {
          "code": 0,
          "extra": "{}"
        },
        "desc": "Burnea Emilian’s comment: Trebuie să ai inimă să înțelegi emoția mesajului acestui om.\nInimă blândă, care efectiv te copleșește.\nRespect. Asta înseamnă patriotism.. Stimă 🤟",
        "title": "#2018 #goviral #viral #romaniaviral #foryou #fypage #foryoupage ",
        "url": "https://m.tiktok.com/v/7442978238504127777.html?_d=49jjef66j4ca6g&comment_author_id=7370361943062119456&preview_pb=0&share_comment_id=7443020462462550817&share_item_id=7442978238504127777&sharer_language=en-US&source=h5_m&u_code=e8hegggb201lba"
      },
      "sort_extra_score": {
        "reply_score": 0.000455,
        "show_more_score": 0.015476
      },
      "sort_tags": "{\"author_digg\":1,\"top_list\":1}",
      "status": 1,
      "stick_position": 0,
      "text": "Trebuie să ai inimă să înțelegi emoția mesajului acestui om.\nInimă blândă, care efectiv te copleșește.\nRespect. Asta înseamnă patriotism.. Stimă 🤟",
      "text_extra": [],
      "trans_btn_style": 1,
      "user": {
        "account_labels": null,
        "ad_cover_url": null,
        "advance_feature_item_order": null,
        "advanced_feature_info": null,
        "avatar_thumb": {
          "uri": "tos-useast2a-avt-0068-euttp/e1a740ee421e6cd51701f6b97b346558",
          "url_list": [
            "https://p16-sign-useast2a.tiktokcdn.com/tos-useast2a-avt-0068-euttp/e1a740ee421e6cd51701f6b97b346558~c5_100x100.jpg?lk3s=30310797&nonce=80360&refresh_token=bd4a6020339c396dd4185047c8acff47&x-expires=1733094000&x-signature=4NyXTEnRNSJhhgJ8%2BPpmjE%2FOFQQ%3D&shp=30310797&shcp=-",
            "https://p16-sign-useast2a.tiktokcdn.com/tos-useast2a-avt-0068-euttp/e1a740ee421e6cd51701f6b97b346558~c5_100x100.jpeg?lk3s=30310797&nonce=78448&refresh_token=c1a9fed5728f9e419bb6fb815786a15c&x-expires=1733094000&x-signature=1bJyma0miYxunBh%2B%2Fm4FVUHm0Qc%3D&shp=30310797&shcp=-"
          ],
          "url_prefix": null
        },
        "bold_fields": null,
        "can_message_follow_status_list": null,
        "can_set_geofencing": null,
        "cha_list": null,
        "cover_url": null,
        "custom_verify": "",
        "enterprise_verify_reason": "",
        "events": null,
        "followers_detail": null,
        "geofencing": null,
        "homepage_bottom_toast": null,
        "item_list": null,
        "mutual_relation_avatars": null,
        "need_points": null,
        "nickname": "Burnea Emilian",
        "platform_sync_info": null,
        "relative_users": null,
        "search_highlight": null,
        "sec_uid": "MS4wLjABAAAA1-vW-yozqm3Sfy7q-HdEI5T__2SUOBsjU3u8TGIssgtSjikQSO_7cF-OkUBWXfx0",
        "shield_edit_field_info": null,
        "type_label": null,
        "uid": "7370361943062119456",
        "unique_id": "burnea.emilian",
        "user_profile_guide": null,
        "user_tags": null,
        "white_cover_url": null
      },
      "user_buried": false,
      "user_digged": 0
    },
    {
      "author_pin": false,
      "aweme_id": "7442978238504127777",
      "cid": "7442984709182964502",
      "collect_stat": 0,
      "comment_language": "ro",
      "comment_post_item_ids": null,
      "create_time": 1732954955,
      "digg_count": 684,
      "forbid_reply_with_video": true,
      "image_list": null,
      "is_author_digged": true,
      "is_comment_translatable": true,
      "label_list": [
        {
          "text": "Liked by creator",
          "type": 20
        }
      ],
      "no_show": false,
      "reply_comment": null,
      "reply_comment_total": 10,
      "reply_id": "0",
      "reply_to_reply_id": "0",
      "share_info": {
        "acl": {
          "code": 0,
          "extra": "{}"
        },
        "desc": "Cristina Crs’s comment: plâng când te ascult 🙏🙏🙏🙏 ești trimis de Dumnezeu",
        "title": "#2018 #goviral #viral #romaniaviral #foryou #fypage #foryoupage ",
        "url": "https://m.tiktok.com/v/7442978238504127777.html?_d=49jjef66j4ca6g&comment_author_id=6736923561598927878&preview_pb=0&share_comment_id=7442984709182964502&share_item_id=7442978238504127777&sharer_language=en-US&source=h5_m&u_code=e8hegggb201lba"
      },
      "sort_extra_score": {
        "reply_score": 0.000602,
        "show_more_score": 0.018438
      },
      "sort_tags": "{\"author_digg\":1,\"top_list\":1}",
      "status": 1,
      "stick_position": 0,
      "text": "plâng când te ascult 🙏🙏🙏🙏 ești trimis de Dumnezeu",
      "text_extra": [],
      "trans_btn_style": 1,
      "user": {
        "account_labels": null,
        "ad_cover_url": null,
        "advance_feature_item_order": null,
        "advanced_feature_info": null,
        "avatar_thumb": {
          "uri": "tos-no1a-avt-0068c001-no/7f8f31e0ec641578cbb64bd4af57ea57",
          "url_list": [
            "https://p16-pu-sign-no.tiktokcdn-eu.com/obj/tos-no1a-avt-0068c001-no/7f8f31e0ec641578cbb64bd4af57ea57?lk3s=30310797&nonce=24999&refresh_token=18d0fd8642c40b6dbf1ddf9244c17855&x-expires=1733094000&x-signature=3MkgI9PHV6fDX0%2BAiIjb849lG5g%3D&shp=30310797&shcp=-",
            "https://p19-pu-sign-no.tiktokcdn-eu.com/obj/tos-no1a-avt-0068c001-no/7f8f31e0ec641578cbb64bd4af57ea57?lk3s=30310797&nonce=1712&refresh_token=6331c7946dc714e83f99bc203b4e652f&x-expires=1733094000&x-signature=Nwe8Jch6qG99u5aH45Wqy9iqUMo%3D&shp=30310797&shcp=-"
          ],
          "url_prefix": null
        },
        "bold_fields": null,
        "can_message_follow_status_list": null,
        "can_set_geofencing": null,
        "cha_list": null,
        "cover_url": null,
        "custom_verify": "",
        "enterprise_verify_reason": "",
        "events": null,
        "followers_detail": null,
        "geofencing": null,
        "homepage_bottom_toast": null,
        "item_list": null,
        "mutual_relation_avatars": null,
        "need_points": null,
        "nickname": "Cristina Crs",
        "platform_sync_info": null,
        "relative_users": null,
        "search_highlight": null,
        "sec_uid": "MS4wLjABAAAAYqqJSpUaeVz-a2DDX2cWOVbajqIXt7IDUtpmzf1MRVT86WsmfiqbGbAGvH3vHRby",
        "shield_edit_field_info": null,
        "type_label": null,
        "uid": "6736923561598927878",
        "unique_id": "cristinacrs190",
        "user_profile_guide": null,
        "user_tags": null,
        "white_cover_url": null
      },
      "user_buried": false,
      "user_digged": 0
    },
    {
      "author_pin": false,
      "aweme_id": "7442978238504127777",
      "cid": "7443009174927622934",
      "collect_stat": 0,
      "comment_language": "ro",
      "comment_post_item_ids": null,
      "create_time": 1732960653,
      "digg_count": 150,
      "forbid_reply_with_video": true,
      "image_list": null,
      "is_author_digged": false,
      "is_comment_translatable": true,
      "label_list": null,
      "no_show": false,
      "reply_comment": null,
      "reply_comment_total": 1,
      "reply_id": "0",
      "reply_to_reply_id": "0",
      "share_info": {
        "acl": {
          "code": 0,
          "extra": "{}"
        },
        "desc": "Ionel’s comment: Mulți nu au habar ce inseamana munca în agricultura a oamenilor care vand legume în piată produsele lor nu samsarii care revând ce cumpara pe nimic produsele de la ei !",
        "title": "#2018 #goviral #viral #romaniaviral #foryou #fypage #foryoupage ",
        "url": "https://m.tiktok.com/v/7442978238504127777.html?_d=49jjef66j4ca6g&comment_author_id=7421641973806154785&preview_pb=0&share_comment_id=7443009174927622934&share_item_id=7442978238504127777&sharer_language=en-US&source=h5_m&u_code=e8hegggb201lba"
      },
      "sort_extra_score": {
        "reply_score": 0.000441,
        "show_more_score": 0.020467
      },
      "sort_tags": "{\"top_list\":1}",
      "status": 1,
      "stick_position": 0,
      "text": "Mulți nu au habar ce inseamana munca în agricultura a oamenilor care vand legume în piată produsele lor nu samsarii care revând ce cumpara pe nimic produsele de la ei !",
      "text_extra": [],
      "trans_btn_style": 1,
      "user": {
        "account_labels": null,
        "ad_cover_url": null,
        "advance_feature_item_order": null,
        "advanced_feature_info": null,
        "avatar_thumb": {
          "uri": "tos-useast2a-avt-0068-euttp/9984f9988932fa06fc632e2e7ef0b171",
          "url_list": [
            "https://p16-sign-useast2a.tiktokcdn.com/tos-useast2a-avt-0068-euttp/9984f9988932fa06fc632e2e7ef0b171~c5_100x100.jpg?lk3s=30310797&nonce=92090&refresh_token=30517e07170199f58dc1982510f2ea3b&x-expires=1733094000&x-signature=O%2FXNFylqM20Vf4ZPBKcgXma0asg%3D&shp=30310797&shcp=-",
            "https://p16-sign-useast2a.tiktokcdn.com/tos-useast2a-avt-0068-euttp/9984f9988932fa06fc632e2e7ef0b171~c5_100x100.jpeg?lk3s=30310797&nonce=7867&refresh_token=a0f9c1518dbed9769dd3539b73686263&x-expires=1733094000&x-signature=8UFEHW5rNxAvp0HLtk%2BLWNkSWIA%3D&shp=30310797&shcp=-"
          ],
          "url_prefix": null
        },
        "bold_fields": null,
        "can_message_follow_status_list": null,
        "can_set_geofencing": null,
        "cha_list": null,
        "cover_url": null,
        "custom_verify": "",
        "enterprise_verify_reason": "",
        "events": null,
        "followers_detail": null,
        "geofencing": null,
        "homepage_bottom_toast": null,
        "item_list": null,
        "mutual_relation_avatars": null,
        "need_points": null,
        "nickname": "Ionel",
        "platform_sync_info": null,
        "relative_users": null,
        "search_highlight": null,
        "sec_uid": "MS4wLjABAAAAVhkwcon2v57oeaYdUIiMAwAGOrGTIcgJPyz8xHJbMq_8FrwjMBY9S7UDZMh4XviZ",
        "shield_edit_field_info": null,
        "type_label": null,
        "uid": "7421641973806154785",
        "unique_id": "ionel.luciu3",
        "user_profile_guide": null,
        "user_tags": null,
        "white_cover_url": null
      },
      "user_buried": false,
      "user_digged": 0
    },
    {
      "author_pin": false,
      "aweme_id": "7442978238504127777",
      "cid": "7443015026187174678",
      "collect_stat": 0,
      "comment_language": "ro",
      "comment_post_item_ids": null,
      "create_time": 1732962014,
      "digg_count": 195,
      "forbid_reply_with_video": true,
      "image_list": null,
      "is_author_digged": true,
      "is_comment_translatable": true,
      "label_list": [
        {
          "text": "Liked by creator",
          "type": 20
        }
      ],
      "no_show": false,
      "reply_comment": null,
      "reply_comment_total": 2,
      "reply_id": "0",
      "reply_to_reply_id": "0",
      "share_info": {
        "acl": {
          "code": 0,
          "extra": "{}"
        },
        "desc": "cristy.viky’s comment: doamne imi da lacrimile, deci nu pot crede de unde a aparut omul asta. votam masiv calin georgescu",
        "title": "#2018 #goviral #viral #romaniaviral #foryou #fypage #foryoupage ",
        "url": "https://m.tiktok.com/v/7442978238504127777.html?_d=49jjef66j4ca6g&comment_author_id=7070466665108210694&preview_pb=0&share_comment_id=7443015026187174678&share_item_id=7442978238504127777&sharer_language=en-US&source=h5_m&u_code=e8hegggb201lba"
      },
      "sort_extra_score": {
        "reply_score": 0.000315,
        "show_more_score": 0.015526
      },
      "sort_tags": "{\"author_digg\":1,\"top_list\":1}",
      "status": 1,
      "stick_position": 0,
      "text": "doamne imi da lacrimile, deci nu pot crede de unde a aparut omul asta. votam masiv calin georgescu",
      "text_extra": [],
      "trans_btn_style": 1,
      "user": {
        "account_labels": null,
        "ad_cover_url": null,
        "advance_feature_item_order": null,
        "advanced_feature_info": null,
        "avatar_thumb": {
          "uri": "tos-useast2a-avt-0068-euttp/d075b1b39bf26902bf45001f6125c8ec",
          "url_list": [
            "https://p16-sign-useast2a.tiktokcdn.com/tos-useast2a-avt-0068-euttp/d075b1b39bf26902bf45001f6125c8ec~c5_100x100.jpg?lk3s=30310797&nonce=24335&refresh_token=655b895712616cf55666557ae67fe55f&x-expires=1733094000&x-signature=qOiKkMGA2j%2B1B2%2Ba8tksTh1VG8s%3D&shp=30310797&shcp=-",
            "https://p16-sign-useast2a.tiktokcdn.com/tos-useast2a-avt-0068-euttp/d075b1b39bf26902bf45001f6125c8ec~c5_100x100.jpeg?lk3s=30310797&nonce=77688&refresh_token=5fc653e0914b2e9578fc52a961b5e117&x-expires=1733094000&x-signature=3vdD9sCZVoTmGmm9svixlpFrKdQ%3D&shp=30310797&shcp=-"
          ],
          "url_prefix": null
        },
        "bold_fields": null,
        "can_message_follow_status_list": null,
        "can_set_geofencing": null,
        "cha_list": null,
        "cover_url": null,
        "custom_verify": "",
        "enterprise_verify_reason": "",
        "events": null,
        "followers_detail": null,
        "geofencing": null,
        "homepage_bottom_toast": null,
        "item_list": null,
        "mutual_relation_avatars": null,
        "need_points": null,
        "nickname": "cristy.viky",
        "platform_sync_info": null,
        "relative_users": null,
        "search_highlight": null,
        "sec_uid": "MS4wLjABAAAARi9tfaB1UfIyYzwmPTez8UtViDjpq8KhjGaR9QflN_9_M7O_urjdvuZDEOed16_g",
        "shield_edit_field_info": null,
        "type_label": null,
        "uid": "7070466665108210694",
        "unique_id": "cristy.viky",
        "user_profile_guide": null,
        "user_tags": null,
        "white_cover_url": null
      },
      "user_buried": false,
      "user_digged": 0
    },
    {
      "author_pin": false,
      "aweme_id": "7442978238504127777",
      "cid": "7442984348004352790",
      "collect_stat": 0,
      "comment_language": "ro",
      "comment_post_item_ids": null,
      "create_time": 1732954892,
      "digg_count": 133,
      "forbid_reply_with_video": true,
      "image_list": null,
      "is_author_digged": true,
      "is_comment_translatable": true,
      "label_list": [
        {
          "text": "Liked by creator",
          "type": 20
        }
      ],
      "no_show": false,
      "reply_comment": null,
      "reply_comment_total": 1,
      "reply_id": "0",
      "reply_to_reply_id": "0",
      "share_info": {
        "acl": {
          "code": 0,
          "extra": "{}"
        },
        "desc": "Stranger’s comment: Doamne, cat de frumos vorbeste acest OM. Cumva, acest OM, imi da speranta. Speranta ca va fi mai bine si pentru noi. Speranta ca, copiii nostrii au un viitor. Doamne Ajuta Romania! 🇹🇩",
        "title": "#2018 #goviral #viral #romaniaviral #foryou #fypage #foryoupage ",
        "url": "https://m.tiktok.com/v/7442978238504127777.html?_d=49jjef66j4ca6g&comment_author_id=6698271714906653702&preview_pb=0&share_comment_id=7442984348004352790&share_item_id=7442978238504127777&sharer_language=en-US&source=h5_m&u_code=e8hegggb201lba"
      },
      "sort_extra_score": {
        "reply_score": 0.000358,
        "show_more_score": 0.005726
      },
      "sort_tags": "{\"author_digg\":1,\"top_list\":1}",
      "status": 1,
      "stick_position": 0,
      "text": "Doamne, cat de frumos vorbeste acest OM. Cumva, acest OM, imi da speranta. Speranta ca va fi mai bine si pentru noi. Speranta ca, copiii nostrii au un viitor. Doamne Ajuta Romania! 🇹🇩",
      "text_extra": [],
      "trans_btn_style": 1,
      "user": {
        "account_labels": null,
        "ad_cover_url": null,
        "advance_feature_item_order": null,
        "advanced_feature_info": null,
        "avatar_thumb": {
          "uri": "tos-no1a-avt-0068c001-no/8e6e2ccb8eda48f4ec290c09db7b32cb",
          "url_list": [
            "https://p16-pu-sign-no.tiktokcdn-eu.com/obj/tos-no1a-avt-0068c001-no/8e6e2ccb8eda48f4ec290c09db7b32cb?lk3s=30310797&nonce=17413&refresh_token=67376febdea41e341647b1c3b05e9fb3&x-expires=1733094000&x-signature=XDV7f8aZRC4DVrtI2RneZVueXj0%3D&shp=30310797&shcp=-",
            "https://p19-pu-sign-no.tiktokcdn-eu.com/obj/tos-no1a-avt-0068c001-no/8e6e2ccb8eda48f4ec290c09db7b32cb?lk3s=30310797&nonce=73218&refresh_token=bfd89afc60c490e3729bcfd64b002623&x-expires=1733094000&x-signature=cEdoRDJ8NDvMAb1%2BfOBuPTSQ%2FNM%3D&shp=30310797&shcp=-"
          ],
          "url_prefix": null
        },
        "bold_fields": null,
        "can_message_follow_status_list": null,
        "can_set_geofencing": null,
        "cha_list": null,
        "cover_url": null,
        "custom_verify": "",
        "enterprise_verify_reason": "",
        "events": null,
        "followers_detail": null,
        "geofencing": null,
        "homepage_bottom_toast": null,
        "item_list": null,
        "mutual_relation_avatars": null,
        "need_points": null,
        "nickname": "Stranger",
        "platform_sync_info": null,
        "relative_users": null,
        "search_highlight": null,
        "sec_uid": "MS4wLjABAAAA3qcELRd7kf1DxyNLCtXiz79kSESrn_PQmP3aS91kcujMTQ306NARfNKgtM2oKkep",
        "shield_edit_field_info": null,
        "type_label": null,
        "uid": "6698271714906653702",
        "unique_id": "strangervl",
        "user_profile_guide": null,
        "user_tags": null,
        "white_cover_url": null
      },
      "user_buried": false,
      "user_digged": 0
    },
    {
      "author_pin": false,
      "aweme_id": "7442978238504127777",
      "cid": "7443015454757995286",
      "collect_stat": 0,
      "comment_language": "fr",
      "comment_post_item_ids": null,
      "create_time": 1732962124,
      "digg_count": 39,
      "forbid_reply_with_video": true,
      "image_list": null,
      "is_author_digged": false,
      "is_comment_translatable": true,
      "label_list": null,
      "no_show": false,
      "reply_comment": null,
      "reply_comment_total": 67,
      "reply_id": "0",
      "reply_to_reply_id": "0",
      "share_info": {
        "acl": {
          "code": 0,
          "extra": "{}"
        },
        "desc": "Cristina Radu’s comment: votez Lasconi",
        "title": "#2018 #goviral #viral #romaniaviral #foryou #fypage #foryoupage ",
        "url": "https://m.tiktok.com/v/7442978238504127777.html?_d=49jjef66j4ca6g&comment_author_id=56506653121978368&preview_pb=0&share_comment_id=7443015454757995286&share_item_id=7442978238504127777&sharer_language=en-US&source=h5_m&u_code=e8hegggb201lba"
      },
      "sort_extra_score": {
        "reply_score": 0.005441,
        "show_more_score": 0.280943
      },
      "sort_tags": "{\"top_list\":1}",
      "status": 1,
      "stick_position": 0,
      "text": "votez Lasconi",
      "text_extra": [],
      "trans_btn_style": 1,
      "user": {
        "account_labels": null,
        "ad_cover_url": null,
        "advance_feature_item_order": null,
        "advanced_feature_info": null,
        "avatar_thumb": {
          "uri": "tos-useast2a-avt-0068-euttp/3f82948f47e764a1d1ff84d2eb04c950",
          "url_list": [
            "https://p16-sign-useast2a.tiktokcdn.com/tos-useast2a-avt-0068-euttp/3f82948f47e764a1d1ff84d2eb04c950~c5_100x100.jpg?lk3s=30310797&nonce=86828&refresh_token=d1c9b85476e0c659879988e1111e3d1b&x-expires=1733094000&x-signature=7c8oHK6E%2F19snz0f3LRbFitjpNs%3D&shp=30310797&shcp=-",
            "https://p16-sign-useast2a.tiktokcdn.com/tos-useast2a-avt-0068-euttp/3f82948f47e764a1d1ff84d2eb04c950~c5_100x100.jpeg?lk3s=30310797&nonce=38708&refresh_token=ea8d0ac85cf7dc87735b206f9f50d5c5&x-expires=1733094000&x-signature=Dxz%2B4KcO%2FvOGPE%2B4uFY0SSonQe4%3D&shp=30310797&shcp=-"
          ],
          "url_prefix": null
        },
        "bold_fields": null,
        "can_message_follow_status_list": null,
        "can_set_geofencing": null,
        "cha_list": null,
        "cover_url": null,
        "custom_verify": "",
        "enterprise_verify_reason": "",
        "events": null,
        "followers_detail": null,
        "geofencing": null,
        "homepage_bottom_toast": null,
        "item_list": null,
        "mutual_relation_avatars": null,
        "need_points": null,
        "nickname": "Cristina Radu",
        "platform_sync_info": null,
        "relative_users": null,
        "search_highlight": null,
        "sec_uid": "MS4wLjABAAAAxVgnhMyfOMpxCr-Y8QSoWMdd5MZzGuMuG9W34miHivHLYpER28yQY3j5x2lrrZUA",
        "shield_edit_field_info": null,
        "type_label": null,
        "uid": "56506653121978368",
        "unique_id": "christina._.radu",
        "user_profile_guide": null,
        "user_tags": null,
        "white_cover_url": null
      },
      "user_buried": false,
      "user_digged": 0
    },
    {
      "author_pin": false,
      "aweme_id": "7442978238504127777",
      "cid": "7443171265366491959",
      "collect_stat": 0,
      "comment_language": "ro",
      "comment_post_item_ids": null,
      "create_time": 1732998376,
      "digg_count": 16,
      "forbid_reply_with_video": true,
      "image_list": null,
      "is_author_digged": false,
      "is_comment_translatable": true,
      "label_list": null,
      "no_show": false,
      "reply_comment": null,
      "reply_comment_total": 1,
      "reply_id": "0",
      "reply_to_reply_id": "0",
      "share_info": {
        "acl": {
          "code": 0,
          "extra": "{}"
        },
        "desc": "MARMAX’s comment: din Republica Moldova ,,as dori asa un Președinte ,,",
        "title": "#2018 #goviral #viral #romaniaviral #foryou #fypage #foryoupage ",
        "url": "https://m.tiktok.com/v/7442978238504127777.html?_d=49jjef66j4ca6g&comment_author_id=7040530123547755526&preview_pb=0&share_comment_id=7443171265366491959&share_item_id=7442978238504127777&sharer_language=en-US&source=h5_m&u_code=e8hegggb201lba"
      },
      "sort_extra_score": {
        "reply_score": 0.000637,
        "show_more_score": 0.017517
      },
      "sort_tags": "{\"top_list\":1}",
      "status": 1,
      "stick_position": 0,
      "text": "din Republica Moldova ,,as dori asa un Președinte ,,",
      "text_extra": [],
      "trans_btn_style": 1,
      "user": {
        "account_labels": null,
        "ad_cover_url": null,
        "advance_feature_item_order": null,
        "advanced_feature_info": null,
        "avatar_thumb": {
          "uri": "tos-maliva-avt-0068/30d60d955374ae22a3e01fed4eb994a0",
          "url_list": [
            "https://p16-sign-va.tiktokcdn.com/tos-maliva-avt-0068/30d60d955374ae22a3e01fed4eb994a0~c5_100x100.jpg?lk3s=30310797&nonce=90242&refresh_token=9659973ac4c30fa64bf5ecb5c152d457&x-expires=1733094000&x-signature=mS%2BkmcmTbrAUkcnazRkmKXMDDbg%3D&shp=30310797&shcp=-",
            "https://p16-sign-va.tiktokcdn.com/tos-maliva-avt-0068/30d60d955374ae22a3e01fed4eb994a0~c5_100x100.jpeg?lk3s=30310797&nonce=72928&refresh_token=865b3e904f7d20f1f4eb78cd5755b3b4&x-expires=1733094000&x-signature=HLAv3LUj1AQn3loAEevJEDfFMRo%3D&shp=30310797&shcp=-"
          ],
          "url_prefix": null
        },
        "bold_fields": null,
        "can_message_follow_status_list": null,
        "can_set_geofencing": null,
        "cha_list": null,
        "cover_url": null,
        "custom_verify": "",
        "enterprise_verify_reason": "",
        "events": null,
        "followers_detail": null,
        "geofencing": null,
        "homepage_bottom_toast": null,
        "item_list": null,
        "mutual_relation_avatars": null,
        "need_points": null,
        "nickname": "MARMAX",
        "platform_sync_info": null,
        "relative_users": null,
        "search_highlight": null,
        "sec_uid": "MS4wLjABAAAAYuM5pRZXsyX2ZCYZBEJ_AiV-3qe3mXo1VpmHetflcxNeUfi62sh3MefzjlalNk3V",
        "shield_edit_field_info": null,
        "type_label": null,
        "uid": "7040530123547755526",
        "unique_id": "p.a..v..e.l",
        "user_profile_guide": null,
        "user_tags": null,
        "white_cover_url": null
      },
      "user_buried": false,
      "user_digged": 0
    },
    {
      "author_pin": false,
      "aweme_id": "7442978238504127777",
      "cid": "7443110923304174338",
      "collect_stat": 0,
      "comment_language": "ro",
      "comment_post_item_ids": null,
      "create_time": 1732984341,
      "digg_count": 4,
      "forbid_reply_with_video": true,
      "image_list": null,
      "is_author_digged": false,
      "is_comment_translatable": true,
      "label_list": null,
      "no_show": false,
      "reply_comment": null,
      "reply_comment_total": 0,
      "reply_id": "0",
      "reply_to_reply_id": "0",
      "share_info": {
        "acl": {
          "code": 0,
          "extra": "{}"
        },
        "desc": "🪷.•°[𝐋𝐮𝐧𝐧𝐚]°•.🪷’s comment: ::Dumnezeu să-l Binecuvănteze ,pe Călin Georgescu, să fie PREȘEDINTELE României Doamne-ajută AMIN 🙏🙏🙏🫂🇷🇴🇷🇴🇷🇴🕊🕊🕊👏🍀",
        "title": "#2018 #goviral #viral #romaniaviral #foryou #fypage #foryoupage ",
        "url": "https://m.tiktok.com/v/7442978238504127777.html?_d=49jjef66j4ca6g&comment_author_id=7004392063303762949&preview_pb=0&share_comment_id=7443110923304174338&share_item_id=7442978238504127777&sharer_language=en-US&source=h5_m&u_code=e8hegggb201lba"
      },
      "sort_extra_score": {
        "reply_score": 0.000579,
        "show_more_score": 6.6e-05
      },
      "sort_tags": "{\"top_list\":1}",
      "status": 1,
      "stick_position": 0,
      "text": "::Dumnezeu să-l Binecuvănteze ,pe Călin Georgescu, să fie PREȘEDINTELE României Doamne-ajută AMIN 🙏🙏🙏🫂🇷🇴🇷🇴🇷🇴🕊🕊🕊👏🍀",
      "text_extra": [],
      "trans_btn_style": 1,
      "user": {
        "account_labels": null,
        "ad_cover_url": null,
        "advance_feature_item_order": null,
        "advanced_feature_info": null,
        "avatar_thumb": {
          "uri": "tos-useast2a-avt-0068-euttp/109fa3f5ea087c107cb58b8c58f4afdb",
          "url_list": [
            "https://p16-sign-useast2a.tiktokcdn.com/tos-useast2a-avt-0068-euttp/109fa3f5ea087c107cb58b8c58f4afdb~c5_100x100.jpg?lk3s=30310797&nonce=52140&refresh_token=53caa0383dac3258665c7a71e13ef40a&x-expires=1733094000&x-signature=lUXVXwjOjMpttOYd9qE3ACiIhkM%3D&shp=30310797&shcp=-",
            "https://p16-sign-useast2a.tiktokcdn.com/tos-useast2a-avt-0068-euttp/109fa3f5ea087c107cb58b8c58f4afdb~c5_100x100.jpeg?lk3s=30310797&nonce=30466&refresh_token=f3a8fc5a9a266f9cab40d647832332d9&x-expires=1733094000&x-signature=cZvB3pPhT90WZsdQCZCSzuuEM0c%3D&shp=30310797&shcp=-"
          ],
          "url_prefix": null
        },
        "bold_fields": null,
        "can_message_follow_status_list": null,
        "can_set_geofencing": null,
        "cha_list": null,
        "cover_url": null,
        "custom_verify": "",
        "enterprise_verify_reason": "",
        "events": null,
        "followers_detail": null,
        "geofencing": null,
        "homepage_bottom_toast": null,
        "item_list": null,
        "mutual_relation_avatars": null,
        "need_points": null,
        "nickname": "🪷.•°[𝐋𝐮𝐧𝐧𝐚]°•.🪷",
        "platform_sync_info": null,
        "relative_users": null,
        "search_highlight": null,
        "sec_uid": "MS4wLjABAAAAzHLPTGv8PPtjUHZ8sf6VhYJS0gP5aVHiGcwUhptrnTyNACyC-ZNJ-KEhbaKGPOLD",
        "shield_edit_field_info": null,
        "type_label": null,
        "uid": "7004392063303762949",
        "unique_id": "andamariana148",
        "user_profile_guide": null,
        "user_tags": null,
        "white_cover_url": null
      },
      "user_buried": false,
      "user_digged": 0
    },
    {
      "author_pin": false,
      "aweme_id": "7442978238504127777",
      "cid": "7443050564944659222",
      "collect_stat": 0,
      "comment_language": "ro",
      "comment_post_item_ids": null,
      "create_time": 1732970289,
      "digg_count": 13,
      "forbid_reply_with_video": true,
      "image_list": null,
      "is_author_digged": false,
      "is_comment_translatable": true,
      "label_list": null,
      "no_show": false,
      "reply_comment": null,
      "reply_comment_total": 0,
      "reply_id": "0",
      "reply_to_reply_id": "0",
      "share_info": {
        "acl": {
          "code": 0,
          "extra": "{}"
        },
        "desc": "Manea Daniela’s comment: Eu cred ca nu suntem obișnuiți cu un om care are mila și caracterul ca al domnului Geogescu și credem ca e fals pt ca ni se pare ciudat ca un om sa fie bun ne-am obișnuit sa avem neîncredere în oameni",
        "title": "#2018 #goviral #viral #romaniaviral #foryou #fypage #foryoupage ",
        "url": "https://m.tiktok.com/v/7442978238504127777.html?_d=49jjef66j4ca6g&comment_author_id=6717648960284115974&preview_pb=0&share_comment_id=7443050564944659222&share_item_id=7442978238504127777&sharer_language=en-US&source=h5_m&u_code=e8hegggb201lba"
      },
      "sort_extra_score": {
        "reply_score": 0.000462,
        "show_more_score": 6.6e-05
      },
      "sort_tags": "{\"top_list\":1}",
      "status": 1,
      "stick_position": 0,
      "text": "Eu cred ca nu suntem obișnuiți cu un om care are mila și caracterul ca al domnului Geogescu și credem ca e fals pt ca ni se pare ciudat ca un om sa fie bun ne-am obișnuit sa avem neîncredere în oameni",
      "text_extra": [],
      "trans_btn_style": 1,
      "user": {
        "account_labels": null,
        "ad_cover_url": null,
        "advance_feature_item_order": null,
        "advanced_feature_info": null,
        "avatar_thumb": {
          "uri": "tos-useast2a-avt-0068-euttp/e39f55faebcbcd8b7235059f5299de92",
          "url_list": [
            "https://p16-sign-useast2a.tiktokcdn.com/tos-useast2a-avt-0068-euttp/e39f55faebcbcd8b7235059f5299de92~c5_100x100.jpg?lk3s=30310797&nonce=14233&refresh_token=dbfc33382e9c0a104d78177ef76d42bd&x-expires=1733094000&x-signature=QwiyI3DsuzeUUAzSStPJ3Cgo3MI%3D&shp=30310797&shcp=-",
            "https://p16-sign-useast2a.tiktokcdn.com/tos-useast2a-avt-0068-euttp/e39f55faebcbcd8b7235059f5299de92~c5_100x100.jpeg?lk3s=30310797&nonce=53346&refresh_token=a0c8aaf5bd74f54ae199f30cdc110739&x-expires=1733094000&x-signature=pblj6P5kmuUB6Jb9fhj1EvXxq4M%3D&shp=30310797&shcp=-"
          ],
          "url_prefix": null
        },
        "bold_fields": null,
        "can_message_follow_status_list": null,
        "can_set_geofencing": null,
        "cha_list": null,
        "cover_url": null,
        "custom_verify": "",
        "enterprise_verify_reason": "",
        "events": null,
        "followers_detail": null,
        "geofencing": null,
        "homepage_bottom_toast": null,
        "item_list": null,
        "mutual_relation_avatars": null,
        "need_points": null,
        "nickname": "Manea Daniela",
        "platform_sync_info": null,
        "relative_users": null,
        "search_highlight": null,
        "sec_uid": "MS4wLjABAAAAVxySBwGjX2v6IVl1S68r8-qBocdUrU-99Bb_JijsxPpvdH1uPirPhTKx4G6hJvS9",
        "shield_edit_field_info": null,
        "type_label": null,
        "uid": "6717648960284115974",
        "unique_id": "maneadaniela35",
        "user_profile_guide": null,
        "user_tags": null,
        "white_cover_url": null
      },
      "user_buried": false,
      "user_digged": 0
    },
    {
      "author_pin": false,
      "aweme_id": "7442978238504127777",
      "cid": "7442986322158109462",
      "collect_stat": 0,
      "comment_language": "ro",
      "comment_post_item_ids": null,
      "create_time": 1732955343,
      "digg_count": 310,
      "forbid_reply_with_video": true,
      "image_list": null,
      "is_author_digged": true,
      "is_comment_translatable": true,
      "label_list": [
        {
          "text": "Liked by creator",
          "type": 20
        }
      ],
      "no_show": false,
      "reply_comment": null,
      "reply_comment_total": 1,
      "reply_id": "0",
      "reply_to_reply_id": "0",
      "share_info": {
        "acl": {
          "code": 0,
          "extra": "{}"
        },
        "desc": "Pâlșu Constanța’s comment: 🙏🙏Călin Giorgescu președinte",
        "title": "#2018 #goviral #viral #romaniaviral #foryou #fypage #foryoupage ",
        "url": "https://m.tiktok.com/v/7442978238504127777.html?_d=49jjef66j4ca6g&comment_author_id=7133914922321134598&preview_pb=0&share_comment_id=7442986322158109462&share_item_id=7442978238504127777&sharer_language=en-US&source=h5_m&u_code=e8hegggb201lba"
      },
      "sort_extra_score": {
        "reply_score": 0.000156,
        "show_more_score": 0.01561
      },
      "sort_tags": "{\"author_digg\":1,\"top_list\":1}",
      "status": 1,
      "stick_position": 0,
      "text": "🙏🙏Călin Giorgescu președinte",
      "text_extra": [],
      "trans_btn_style": 1,
      "user": {
        "account_labels": null,
        "ad_cover_url": null,
        "advance_feature_item_order": null,
        "advanced_feature_info": null,
        "avatar_thumb": {
          "uri": "tos-useast2a-avt-0068-euttp/caa58eda20943ee5b663d6ab3cbe5f87",
          "url_list": [
            "https://p16-sign-useast2a.tiktokcdn.com/tos-useast2a-avt-0068-euttp/caa58eda20943ee5b663d6ab3cbe5f87~c5_100x100.jpg?lk3s=30310797&nonce=95778&refresh_token=6a4e7d79202e476cd22114351d318f96&x-expires=1733094000&x-signature=Ia8%2FmRMNrN69qUWXjuKLaAFqF4Q%3D&shp=30310797&shcp=-",
            "https://p16-sign-useast2a.tiktokcdn.com/tos-useast2a-avt-0068-euttp/caa58eda20943ee5b663d6ab3cbe5f87~c5_100x100.jpeg?lk3s=30310797&nonce=41391&refresh_token=7bba069aba402ecc4989a84d37346591&x-expires=1733094000&x-signature=mzx7Aryg0YrYlh3%2B51jUN0KxSmw%3D&shp=30310797&shcp=-"
          ],
          "url_prefix": null
        },
        "bold_fields": null,
        "can_message_follow_status_list": null,
        "can_set_geofencing": null,
        "cha_list": null,
        "cover_url": null,
        "custom_verify": "",
        "enterprise_verify_reason": "",
        "events": null,
        "followers_detail": null,
        "geofencing": null,
        "homepage_bottom_toast": null,
        "item_list": null,
        "mutual_relation_avatars": null,
        "need_points": null,
        "nickname": "Pâlșu Constanța",
        "platform_sync_info": null,
        "relative_users": null,
        "search_highlight": null,
        "sec_uid": "MS4wLjABAAAAZsVOSJMfdNj41LLJvUAJ_ZMaTAi8z340WoXGfxvqmxVLwSCK_zEYoKxQ7iZ56icO",
        "shield_edit_field_info": null,
        "type_label": null,
        "uid": "7133914922321134598",
        "unique_id": "user6544621440878",
        "user_profile_guide": null,
        "user_tags": null,
        "white_cover_url": null
      },
      "user_buried": false,
      "user_digged": 0
    },
    {
      "author_pin": false,
      "aweme_id": "7442978238504127777",
      "cid": "7442993340155527958",
      "collect_stat": 0,
      "comment_language": "ro",
      "comment_post_item_ids": null,
      "create_time": 1732956978,
      "digg_count": 156,
      "forbid_reply_with_video": true,
      "image_list": null,
      "is_author_digged": false,
      "is_comment_translatable": true,
      "label_list": null,
      "no_show": false,
      "reply_comment": null,
      "reply_comment_total": 8,
      "reply_id": "0",
      "reply_to_reply_id": "0",
      "share_info": {
        "acl": {
          "code": 0,
          "extra": "{}"
        },
        "desc": "Georgy💎’s comment: doamne ce om inteligent,deci eu plâng de fiecare dată când îl ascult vorbind 🥹👌🏻",
        "title": "#2018 #goviral #viral #romaniaviral #foryou #fypage #foryoupage ",
        "url": "https://m.tiktok.com/v/7442978238504127777.html?_d=49jjef66j4ca6g&comment_author_id=6684837857436206085&preview_pb=0&share_comment_id=7442993340155527958&share_item_id=7442978238504127777&sharer_language=en-US&source=h5_m&u_code=e8hegggb201lba"
      },
      "sort_extra_score": {
        "reply_score": 0.000394,
        "show_more_score": 0.023313
      },
      "sort_tags": "{\"top_list\":1}",
      "status": 1,
      "stick_position": 0,
      "text": "doamne ce om inteligent,deci eu plâng de fiecare dată când îl ascult vorbind 🥹👌🏻",
      "text_extra": [],
      "trans_btn_style": 1,
      "user": {
        "account_labels": null,
        "ad_cover_url": null,
        "advance_feature_item_order": null,
        "advanced_feature_info": null,
        "avatar_thumb": {
          "uri": "tos-useast2a-avt-0068-euttp/18246300829631678e38bdc46c343149",
          "url_list": [
            "https://p16-sign-useast2a.tiktokcdn.com/tos-useast2a-avt-0068-euttp/18246300829631678e38bdc46c343149~c5_100x100.jpg?lk3s=30310797&nonce=14199&refresh_token=11aef67c195d87ca923339179eb2a91f&x-expires=1733094000&x-signature=oTJGfTAmmAvGd%2B%2BXueOELpBnOWM%3D&shp=30310797&shcp=-",
            "https://p16-sign-useast2a.tiktokcdn.com/tos-useast2a-avt-0068-euttp/18246300829631678e38bdc46c343149~c5_100x100.jpeg?lk3s=30310797&nonce=41386&refresh_token=0524f6924c5b80404be329b5895e3b5c&x-expires=1733094000&x-signature=5NKTctXi%2FAGeWqxtfBgEGRMm%2BkI%3D&shp=30310797&shcp=-"
          ],
          "url_prefix": null
        },
        "bold_fields": null,
        "can_message_follow_status_list": null,
        "can_set_geofencing": null,
        "cha_list": null,
        "cover_url": null,
        "custom_verify": "",
        "enterprise_verify_reason": "",
        "events": null,
        "followers_detail": null,
        "geofencing": null,
        "homepage_bottom_toast": null,
        "item_list": null,
        "mutual_relation_avatars": null,
        "need_points": null,
        "nickname": "Georgy💎",
        "platform_sync_info": null,
        "relative_users": null,
        "search_highlight": null,
        "sec_uid": "MS4wLjABAAAA3DYQtNCUpg5l0JooIi_uAT0WNM9Ur6V8FqmP5a2E9oRiUwpxkx6FiQcTk9Cl28H_",
        "shield_edit_field_info": null,
        "type_label": null,
        "uid": "6684837857436206085",
        "unique_id": "georgybia",
        "user_profile_guide": null,
        "user_tags": null,
        "white_cover_url": null
      },
      "user_buried": false,
      "user_digged": 0
    },
    {
      "author_pin": false,
      "aweme_id": "7442978238504127777",
      "cid": "7443149391705867030",
      "collect_stat": 0,
      "comment_language": "ro",
      "comment_post_item_ids": null,
      "create_time": 1732993292,
      "digg_count": 2,
      "forbid_reply_with_video": true,
      "image_list": null,
      "is_author_digged": false,
      "is_comment_translatable": true,
      "label_list": null,
      "no_show": false,
      "reply_comment": null,
      "reply_comment_total": 0,
      "reply_id": "0",
      "reply_to_reply_id": "0",
      "share_info": {
        "acl": {
          "code": 0,
          "extra": "{}"
        },
        "desc": "Fagateanu Iany’s comment: Este foarte inteligent ❤",
        "title": "#2018 #goviral #viral #romaniaviral #foryou #fypage #foryoupage ",
        "url": "https://m.tiktok.com/v/7442978238504127777.html?_d=49jjef66j4ca6g&comment_author_id=6801361666572289029&preview_pb=0&share_comment_id=7443149391705867030&share_item_id=7442978238504127777&sharer_language=en-US&source=h5_m&u_code=e8hegggb201lba"
      },
      "sort_extra_score": {
        "reply_score": 0.00041,
        "show_more_score": 2.5e-05
      },
      "sort_tags": "{\"top_list\":1}",
      "status": 1,
      "stick_position": 0,
      "text": "Este foarte inteligent ❤",
      "text_extra": [],
      "trans_btn_style": 1,
      "user": {
        "account_labels": null,
        "ad_cover_url": null,
        "advance_feature_item_order": null,
        "advanced_feature_info": null,
        "avatar_thumb": {
          "uri": "tos-maliva-avt-0068/c93016eb08635e927448404fc6a0de90",
          "url_list": [
            "https://p16-sign-va.tiktokcdn.com/tos-maliva-avt-0068/c93016eb08635e927448404fc6a0de90~c5_100x100.jpg?lk3s=30310797&nonce=37965&refresh_token=0c8a2d9aa39e023cb04e72f0814321d9&x-expires=1733094000&x-signature=kHupB%2F%2BtPImb0%2FmsdvwFCYafwcs%3D&shp=30310797&shcp=-",
            "https://p16-sign-va.tiktokcdn.com/tos-maliva-avt-0068/c93016eb08635e927448404fc6a0de90~c5_100x100.jpeg?lk3s=30310797&nonce=11413&refresh_token=bcd063e2171662be1d84b475e8588f00&x-expires=1733094000&x-signature=F0CSWkIm6PRzElbd0FuZdnW%2Fj%2Fs%3D&shp=30310797&shcp=-"
          ],
          "url_prefix": null
        },
        "bold_fields": null,
        "can_message_follow_status_list": null,
        "can_set_geofencing": null,
        "cha_list": null,
        "cover_url": null,
        "custom_verify": "",
        "enterprise_verify_reason": "",
        "events": null,
        "followers_detail": null,
        "geofencing": null,
        "homepage_bottom_toast": null,
        "item_list": null,
        "mutual_relation_avatars": null,
        "need_points": null,
        "nickname": "Fagateanu Iany",
        "platform_sync_info": null,
        "relative_users": null,
        "search_highlight": null,
        "sec_uid": "MS4wLjABAAAAAywCbV9aYTe3LLN0q5W-Q1cCAafbOVpb5pS-dzbVNzw37z3hio7-JVQmD4trTirb",
        "shield_edit_field_info": null,
        "type_label": null,
        "uid": "6801361666572289029",
        "unique_id": "fagateanuiany",
        "user_profile_guide": null,
        "user_tags": null,
        "white_cover_url": null
      },
      "user_buried": false,
      "user_digged": 0
    },
    {
      "author_pin": false,
      "aweme_id": "7442978238504127777",
      "cid": "7442988986464797463",
      "collect_stat": 0,
      "comment_language": "ro",
      "comment_post_item_ids": null,
      "create_time": 1732955962,
      "digg_count": 41,
      "forbid_reply_with_video": true,
      "image_list": null,
      "is_author_digged": false,
      "is_comment_translatable": true,
      "label_list": null,
      "no_show": false,
      "reply_comment": null,
      "reply_comment_total": 0,
      "reply_id": "0",
      "reply_to_reply_id": "0",
      "share_info": {
        "acl": {
          "code": 0,
          "extra": "{}"
        },
        "desc": "Ana-Maria’s comment: Doamne cât adevăr în tot ceea ce spune!!!🙏🙏🙏",
        "title": "#2018 #goviral #viral #romaniaviral #foryou #fypage #foryoupage ",
        "url": "https://m.tiktok.com/v/7442978238504127777.html?_d=49jjef66j4ca6g&comment_author_id=7441649371491894304&preview_pb=0&share_comment_id=7442988986464797463&share_item_id=7442978238504127777&sharer_language=en-US&source=h5_m&u_code=e8hegggb201lba"
      },
      "sort_extra_score": {
        "reply_score": 0.000212,
        "show_more_score": 1.6e-05
      },
      "sort_tags": "{\"top_list\":1}",
      "status": 1,
      "stick_position": 0,
      "text": "Doamne cât adevăr în tot ceea ce spune!!!🙏🙏🙏",
      "text_extra": [],
      "trans_btn_style": 1,
      "user": {
        "account_labels": null,
        "ad_cover_url": null,
        "advance_feature_item_order": null,
        "advanced_feature_info": null,
        "avatar_thumb": {
          "uri": "tos-no1a-avt-0068c001-no/56bfa9558a47bff77205fcf5019c8508",
          "url_list": [
            "https://p16-pu-sign-no.tiktokcdn-eu.com/obj/tos-no1a-avt-0068c001-no/56bfa9558a47bff77205fcf5019c8508?lk3s=30310797&nonce=26529&refresh_token=fdb2d018b7a693add40b4169ab6c5aed&x-expires=1733094000&x-signature=hc7vZ9zdbHszm39d82XXhzBEx24%3D&shp=30310797&shcp=-",
            "https://p19-pu-sign-no.tiktokcdn-eu.com/obj/tos-no1a-avt-0068c001-no/56bfa9558a47bff77205fcf5019c8508?lk3s=30310797&nonce=93547&refresh_token=347e41b718e64fc4937fb964679e8a32&x-expires=1733094000&x-signature=pPRBmQRKVByUcKUVfbl6g%2Fksoks%3D&shp=30310797&shcp=-"
          ],
          "url_prefix": null
        },
        "bold_fields": null,
        "can_message_follow_status_list": null,
        "can_set_geofencing": null,
        "cha_list": null,
        "cover_url": null,
        "custom_verify": "",
        "enterprise_verify_reason": "",
        "events": null,
        "followers_detail": null,
        "geofencing": null,
        "homepage_bottom_toast": null,
        "item_list": null,
        "mutual_relation_avatars": null,
        "need_points": null,
        "nickname": "Ana-Maria",
        "platform_sync_info": null,
        "relative_users": null,
        "search_highlight": null,
        "sec_uid": "MS4wLjABAAAA7qS2ewUrhgW4a3kOl_Jj5aPtwgAkjHbbO9Xj8g7Q2RL5ewuTiDkD0O0LT6H2lthH",
        "shield_edit_field_info": null,
        "type_label": null,
        "uid": "7441649371491894304",
        "unique_id": "user9315274725817",
        "user_profile_guide": null,
        "user_tags": null,
        "white_cover_url": null
      },
      "user_buried": false,
      "user_digged": 0
    },
    {
      "author_pin": false,
      "aweme_id": "7442978238504127777",
      "cid": "7442988467300598561",
      "collect_stat": 0,
      "comment_language": "ro",
      "comment_post_item_ids": null,
      "create_time": 1732955819,
      "digg_count": 135,
      "forbid_reply_with_video": true,
      "image_list": null,
      "is_author_digged": true,
      "is_comment_translatable": true,
      "label_list": [
        {
          "text": "Liked by creator",
          "type": 20
        }
      ],
      "no_show": false,
      "reply_comment": null,
      "reply_comment_total": 2,
      "reply_id": "0",
      "reply_to_reply_id": "0",
      "share_info": {
        "acl": {
          "code": 0,
          "extra": "{}"
        },
        "desc": "*coco’s comment: mau dat lacrimile sincer este un om cu suflet bun sper sa ajunga acolo unde trebuie dumnezeu sa fie cu noi",
        "title": "#2018 #goviral #viral #romaniaviral #foryou #fypage #foryoupage ",
        "url": "https://m.tiktok.com/v/7442978238504127777.html?_d=49jjef66j4ca6g&comment_author_id=6549563350043333647&preview_pb=0&share_comment_id=7442988467300598561&share_item_id=7442978238504127777&sharer_language=en-US&source=h5_m&u_code=e8hegggb201lba"
      },
      "sort_extra_score": {
        "reply_score": 0.000551,
        "show_more_score": 0.008601
      },
      "sort_tags": "{\"author_digg\":1,\"top_list\":1}",
      "status": 1,
      "stick_position": 0,
      "text": "mau dat lacrimile sincer este un om cu suflet bun sper sa ajunga acolo unde trebuie dumnezeu sa fie cu noi",
      "text_extra": [],
      "trans_btn_style": 1,
      "user": {
        "account_labels": null,
        "ad_cover_url": null,
        "advance_feature_item_order": null,
        "advanced_feature_info": null,
        "avatar_thumb": {
          "uri": "tos-useast2a-avt-0068-euttp/9b91c344f51319a2676495926c898865",
          "url_list": [
            "https://p16-sign-useast2a.tiktokcdn.com/tos-useast2a-avt-0068-euttp/9b91c344f51319a2676495926c898865~c5_100x100.jpg?lk3s=30310797&nonce=85041&refresh_token=dca84969879c8005f5f563f8bc0f88a0&x-expires=1733094000&x-signature=aW1nncs4Uiyl1Kz8d10tsmt8zXk%3D&shp=30310797&shcp=-",
            "https://p16-sign-useast2a.tiktokcdn.com/tos-useast2a-avt-0068-euttp/9b91c344f51319a2676495926c898865~c5_100x100.jpeg?lk3s=30310797&nonce=33722&refresh_token=2a670c13d6c3c84544a7c820d3633e70&x-expires=1733094000&x-signature=DH22Z7qi770uPdlj8Lkintx%2BCSk%3D&shp=30310797&shcp=-"
          ],
          "url_prefix": null
        },
        "bold_fields": null,
        "can_message_follow_status_list": null,
        "can_set_geofencing": null,
        "cha_list": null,
        "cover_url": null,
        "custom_verify": "",
        "enterprise_verify_reason": "",
        "events": null,
        "followers_detail": null,
        "geofencing": null,
        "homepage_bottom_toast": null,
        "item_list": null,
        "mutual_relation_avatars": null,
        "need_points": null,
        "nickname": "*coco",
        "platform_sync_info": null,
        "relative_users": null,
        "search_highlight": null,
        "sec_uid": "MS4wLjABAAAAd0_M_n9h6iQCkqUs9kV62py4-YHt0nv5_qukDmgYiEn6ZvEw50D_Q7jz65PlyjgI",
        "shield_edit_field_info": null,
        "type_label": null,
        "uid": "6549563350043333647",
        "unique_id": "coco..coco.d",
        "user_profile_guide": null,
        "user_tags": null,
        "white_cover_url": null
      },
      "user_buried": false,
      "user_digged": 0
    },
    {
      "author_pin": false,
      "aweme_id": "7442978238504127777",
      "cid": "7443010599645430550",
      "collect_stat": 0,
      "comment_language": "ro",
      "comment_post_item_ids": null,
      "create_time": 1732960996,
      "digg_count": 18,
      "forbid_reply_with_video": true,
      "image_list": null,
      "is_author_digged": false,
      "is_comment_translatable": true,
      "label_list": null,
      "no_show": false,
      "reply_comment": null,
      "reply_comment_total": 1,
      "reply_id": "0",
      "reply_to_reply_id": "0",
      "share_info": {
        "acl": {
          "code": 0,
          "extra": "{}"
        },
        "desc": "sorinprepelita891’s comment: Dumnezeu la trimis pe acest om minunat sa salveze Romania!🙏🙏🙏🥰",
        "title": "#2018 #goviral #viral #romaniaviral #foryou #fypage #foryoupage ",
        "url": "https://m.tiktok.com/v/7442978238504127777.html?_d=49jjef66j4ca6g&comment_author_id=6976937271188014085&preview_pb=0&share_comment_id=7443010599645430550&share_item_id=7442978238504127777&sharer_language=en-US&source=h5_m&u_code=e8hegggb201lba"
      },
      "sort_extra_score": {
        "reply_score": 0.000271,
        "show_more_score": 0.017911
      },
      "sort_tags": "{\"top_list\":1}",
      "status": 1,
      "stick_position": 0,
      "text": "Dumnezeu la trimis pe acest om minunat sa salveze Romania!🙏🙏🙏🥰",
      "text_extra": [],
      "trans_btn_style": 1,
      "user": {
        "account_labels": null,
        "ad_cover_url": null,
        "advance_feature_item_order": null,
        "advanced_feature_info": null,
        "avatar_thumb": {
          "uri": "tos-useast2a-avt-0068-euttp/416fedf68c9f9ade9c490835e1fa4741",
          "url_list": [
            "https://p16-sign-useast2a.tiktokcdn.com/tos-useast2a-avt-0068-euttp/416fedf68c9f9ade9c490835e1fa4741~c5_100x100.jpg?lk3s=30310797&nonce=65896&refresh_token=e048e7b8770727b67ee70d78030f99dd&x-expires=1733094000&x-signature=zRmvTQn80y0CNH6rLi9kNsX6r4Y%3D&shp=30310797&shcp=-",
            "https://p16-sign-useast2a.tiktokcdn.com/tos-useast2a-avt-0068-euttp/416fedf68c9f9ade9c490835e1fa4741~c5_100x100.jpeg?lk3s=30310797&nonce=45559&refresh_token=47704ec8440395ae84131e3bfa2e1aa3&x-expires=1733094000&x-signature=PCp%2F1zobgoS61RhZF7K4Wel7rZw%3D&shp=30310797&shcp=-"
          ],
          "url_prefix": null
        },
        "bold_fields": null,
        "can_message_follow_status_list": null,
        "can_set_geofencing": null,
        "cha_list": null,
        "cover_url": null,
        "custom_verify": "",
        "enterprise_verify_reason": "",
        "events": null,
        "followers_detail": null,
        "geofencing": null,
        "homepage_bottom_toast": null,
        "item_list": null,
        "mutual_relation_avatars": null,
        "need_points": null,
        "nickname": "sorinprepelita891",
        "platform_sync_info": null,
        "relative_users": null,
        "search_highlight": null,
        "sec_uid": "MS4wLjABAAAA3eLrNSqnr4sAmIcP7YflaOWPwmsb3-ufTCmyng9KqOPvg-zn-vTJJQi8nGUQ6sXq",
        "shield_edit_field_info": null,
        "type_label": null,
        "uid": "6976937271188014085",
        "unique_id": "sorinprepelita891",
        "user_profile_guide": null,
        "user_tags": null,
        "white_cover_url": null
      },
      "user_buried": false,
      "user_digged": 0
    },
    {
      "author_pin": false,
      "aweme_id": "7442978238504127777",
      "cid": "7442985242690306838",
      "collect_stat": 0,
      "comment_language": "ro",
      "comment_post_item_ids": null,
      "create_time": 1732955083,
      "digg_count": 314,
      "forbid_reply_with_video": true,
      "image_list": null,
      "is_author_digged": true,
      "is_comment_translatable": true,
      "label_list": [
        {
          "text": "Liked by creator",
          "type": 20
        }
      ],
      "no_show": false,
      "reply_comment": null,
      "reply_comment_total": 6,
      "reply_id": "0",
      "reply_to_reply_id": "0",
      "share_info": {
        "acl": {
          "code": 0,
          "extra": "{}"
        },
        "desc": "mavi’s comment: Chiar așa mi s-a întâmplat și mie ! Când merg la piață mă uit tot timpul după bătrânei nu după bișnițari! Trist dar adevărat !",
        "title": "#2018 #goviral #viral #romaniaviral #foryou #fypage #foryoupage ",
        "url": "https://m.tiktok.com/v/7442978238504127777.html?_d=49jjef66j4ca6g&comment_author_id=7441990284726993942&preview_pb=0&share_comment_id=7442985242690306838&share_item_id=7442978238504127777&sharer_language=en-US&source=h5_m&u_code=e8hegggb201lba"
      },
      "sort_extra_score": {
        "reply_score": 0.000302,
        "show_more_score": 0.014374
      },
      "sort_tags": "{\"author_digg\":1,\"top_list\":1}",
      "status": 1,
      "stick_position": 0,
      "text": "Chiar așa mi s-a întâmplat și mie ! Când merg la piață mă uit tot timpul după bătrânei nu după bișnițari! Trist dar adevărat !",
      "text_extra": [],
      "trans_btn_style": 1,
      "user": {
        "account_labels": null,
        "ad_cover_url": null,
        "advance_feature_item_order": null,
        "advanced_feature_info": null,
        "avatar_thumb": {
          "uri": "musically-maliva-obj/1594805258216454",
          "url_list": [
            "https://p16-sign-va.tiktokcdn.com/musically-maliva-obj/1594805258216454~c5_100x100.jpg?lk3s=30310797&nonce=76970&refresh_token=f69a7a443ab3277dac9fbf0732d1e82e&x-expires=1733094000&x-signature=88S4txMg8njxffS0uuBQ5y4RqEM%3D&shp=30310797&shcp=-",
            "https://p16-sign-va.tiktokcdn.com/musically-maliva-obj/1594805258216454~c5_100x100.jpeg?lk3s=30310797&nonce=76867&refresh_token=d5af75eb275d0c27fbd4173c5c2d7738&x-expires=1733094000&x-signature=2Jni8InoYc7g7hDs5B09p2aIoUM%3D&shp=30310797&shcp=-"
          ],
          "url_prefix": null
        },
        "bold_fields": null,
        "can_message_follow_status_list": null,
        "can_set_geofencing": null,
        "cha_list": null,
        "cover_url": null,
        "custom_verify": "",
        "enterprise_verify_reason": "",
        "events": null,
        "followers_detail": null,
        "geofencing": null,
        "homepage_bottom_toast": null,
        "item_list": null,
        "mutual_relation_avatars": null,
        "need_points": null,
        "nickname": "mavi",
        "platform_sync_info": null,
        "relative_users": null,
        "search_highlight": null,
        "sec_uid": "MS4wLjABAAAALicBubCBWaMVCRpFmMRi89yuKQgBZCHnq0F40KlWK_jpVkx-HnKu6eeW-lFe9XrU",
        "shield_edit_field_info": null,
        "type_label": null,
        "uid": "7441990284726993942",
        "unique_id": "mavi62559",
        "user_profile_guide": null,
        "user_tags": null,
        "white_cover_url": null
      },
      "user_buried": false,
      "user_digged": 0
    },
    {
      "author_pin": false,
      "aweme_id": "7442978238504127777",
      "cid": "7442985237956428567",
      "collect_stat": 0,
      "comment_language": "ro",
      "comment_post_item_ids": null,
      "create_time": 1732955091,
      "digg_count": 54,
      "forbid_reply_with_video": true,
      "image_list": null,
      "is_author_digged": true,
      "is_comment_translatable": true,
      "label_list": [
        {
          "text": "Liked by creator",
          "type": 20
        }
      ],
      "no_show": false,
      "reply_comment": null,
      "reply_comment_total": 1,
      "reply_id": "0",
      "reply_to_reply_id": "0",
      "share_info": {
        "acl": {
          "code": 0,
          "extra": "{}"
        },
        "desc": "Danmihai’s comment: Dumnezeu a întors fata spre noi Romanii,Doamne multumim!Când sufletul îl simți alinat de Dumnezeu,trebuie sa urmam calea!",
        "title": "#2018 #goviral #viral #romaniaviral #foryou #fypage #foryoupage ",
        "url": "https://m.tiktok.com/v/7442978238504127777.html?_d=49jjef66j4ca6g&comment_author_id=7179377163073504261&preview_pb=0&share_comment_id=7442985237956428567&share_item_id=7442978238504127777&sharer_language=en-US&source=h5_m&u_code=e8hegggb201lba"
      },
      "sort_extra_score": {
        "reply_score": 0.000354,
        "show_more_score": 0.007596
      },
      "sort_tags": "{\"author_digg\":1,\"top_list\":1}",
      "status": 1,
      "stick_position": 0,
      "text": "Dumnezeu a întors fata spre noi Romanii,Doamne multumim!Când sufletul îl simți alinat de Dumnezeu,trebuie sa urmam calea!",
      "text_extra": [],
      "trans_btn_style": 1,
      "user": {
        "account_labels": null,
        "ad_cover_url": null,
        "advance_feature_item_order": null,
        "advanced_feature_info": null,
        "avatar_thumb": {
          "uri": "tos-useast2a-avt-0068-euttp/7244606787955982362",
          "url_list": [
            "https://p16-sign-useast2a.tiktokcdn.com/tos-useast2a-avt-0068-euttp/7244606787955982362~c5_100x100.jpg?lk3s=30310797&nonce=62604&refresh_token=2fbf8052d20e2e6b43e3ac50091a16c2&x-expires=1733094000&x-signature=vukaLIhY4ZVe3vhSYWQihK3vEVE%3D&shp=30310797&shcp=-",
            "https://p16-sign-useast2a.tiktokcdn.com/tos-useast2a-avt-0068-euttp/7244606787955982362~c5_100x100.jpeg?lk3s=30310797&nonce=637&refresh_token=06df9b4b339d0ebde8ab64bd6dffc1da&x-expires=1733094000&x-signature=5FDuC5lb%2F8oN%2FpFW5qJPFvwzj%2Bk%3D&shp=30310797&shcp=-"
          ],
          "url_prefix": null
        },
        "bold_fields": null,
        "can_message_follow_status_list": null,
        "can_set_geofencing": null,
        "cha_list": null,
        "cover_url": null,
        "custom_verify": "",
        "enterprise_verify_reason": "",
        "events": null,
        "followers_detail": null,
        "geofencing": null,
        "homepage_bottom_toast": null,
        "item_list": null,
        "mutual_relation_avatars": null,
        "need_points": null,
        "nickname": "Danmihai",
        "platform_sync_info": null,
        "relative_users": null,
        "search_highlight": null,
        "sec_uid": "MS4wLjABAAAAcFJZ-rfXbgWE0qAuTFpLMiZj3EJJW4bzSoLk3H6bvjmoxhxz1NXX05Bl-QGx7qUX",
        "shield_edit_field_info": null,
        "type_label": null,
        "uid": "7179377163073504261",
        "unique_id": "danmihai6952",
        "user_profile_guide": null,
        "user_tags": null,
        "white_cover_url": null
      },
      "user_buried": false,
      "user_digged": 0
    }
  ]
}