<output>
<analysis>
Let's analyze this post according to our criteria:

1. Has CMF: Yes - "CMF 11240002" is present at the end of the post, indicating this is electoral propaganda material.

2. Refers to candidate: Yes - The post explicitly mentions two presidential candidates:
- Marcel Ciolacu (negatively)
- Nicolae Ciucă (positively)

3. Addresses wide population: Yes
- It's a paid Facebook/Instagram post
- Uses collective addressing ("să votăm", "avem o șansă")
- Targets a large estimated audience (100,001-500,000 people)

4. Electoral objective: Yes
- Explicitly calls for voting ("votați Nicolae Ciucă")
- Presents a clear electoral message
- Attempts to influence voting behavior through negative portrayal of one candidate and positive portrayal of another
- Specifically mentions "această duminică" referring to election day

5. Journalism: No
- This is not journalistic content
- Contains clear partisan messaging and call to action
- Uses emotional language and campaign rhetoric

6. Personal opinion: No
- This is a structured campaign message
- Contains CMF number
- Is a paid advertisement
- Has clear electoral objectives
</analysis>

<conclusion>
<post_id>3743931592523454</post_id>
<electoral-propaganda-analysis>
This is clearly electoral propaganda because:
- Contains CMF number
- Direct call to vote for a specific candidate
- Negative campaigning against another candidate
- Paid distribution
- Clear electoral messaging
- Timing coincides with presidential campaign
- References the upcoming election day specifically
</electoral-propaganda-analysis>
<electoral-propaganda-decision>TRUE</electoral-propaganda-decision>
<electoral-propaganda-candidates>
  <candidate><name>NICOLAE-IONEL CIUCĂ</name><impact>POSITIVE</impact></candidate>
  <candidate><name>ION-MARCEL CIOLACU</name><impact>NEGATIVE</impact></candidate>
</electoral-propaganda-candidates>
<responsible-party-or-group>PNL</responsible-party-or-group>
<message-for-police>
Alin Calinescu, pentru incalcarea articolului 55 t) din Legea 370/2004, prin continuarea propagandei electorale după încheierea campaniei, prin postarea cu ID 3743931592523454 pe Facebook după ora 18:00 pe 23.11.2024. Postarea constituie propagandă electorală conform art. 36(7) din Legea 334/2006, conținând materiale care se referă direct la candidații Nicolae Ciucă și Marcel Ciolacu, având obiectiv electoral explicit prin îndemnul "votați Nicolae Ciucă", adresându-se publicului larg prin distribuție plătită pe Facebook și Instagram. Postarea include număr CMF (11240002), confirmând natura sa de material de propagandă electorală, și face referire directă la "această duminică" în contextul alegerilor prezidențiale, încercând să influențeze comportamentul electoral prin prezentarea contrastantă a celor doi candidați.
</message-for-police>
</conclusion>
</output>