<output>
<analysis>
Let's analyze this post according to our criteria:

1. Has CMF: No CMF number is present in the post.

2. Refers to candidate: Yes, it directly refers to Nicolae-Ionel Ciucă, a presidential candidate, and mentions him specifically.

3. Addresses wide population: Yes, this is a paid Facebook advertisement targeting a potentially large audience (estimated 1,000,001+ reach).

4. Electoral objective: Yes, the content explicitly asks PNL members not to vote for Ciucă ("Nu vă cer să-l retrageți pe Ciucă, vă cer să nu-l votați!"), which is a clear electoral objective.

5. Journalism: No, this is not journalism. It's presented as an open letter ("Scrisoare deschisă") with a clear political stance and call to action.

6. Personal opinion: While formatted as an opinion piece, the fact that it's a paid advertisement with significant reach and explicit voting instructions makes it cross the line into electoral propaganda.

This post is clearly electoral propaganda because:
- It directly targets a presidential candidate
- Has a clear call to action regarding voting
- Is being promoted through paid advertising
- Reaches a wide audience
- Has a clear electoral objective to influence voting behavior
</analysis>

<conclusion>
<post_id>1598757470719860</post_id>
<electoral-propaganda-analysis>
This post constitutes electoral propaganda as it:
1. Directly names and targets a presidential candidate
2. Makes an explicit call not to vote for the candidate
3. Is distributed through paid advertising
4. Reaches a wide audience
5. Has clear electoral objectives
</electoral-propaganda-analysis>
<electoral-propaganda-decision>TRUE</electoral-propaganda-decision>
<electoral-propaganda-candidates>
<candidate>
<name>NICOLAE-IONEL CIUCĂ</name>
<impact>NEGATIVE</impact>
</candidate>
</electoral-propaganda-candidates>
<responsible-party-or-group>INDEPENDENT</responsible-party-or-group>
<message-for-police>
Comunitatea Liberală, pentru incalcarea articolului 55 t) din Legea 370/2004, prin publicarea și promovarea unei reclame platite pe Facebook (ID: 1598757470719860) după ora 18:00 pe 23.11.2024, în care se face în mod explicit propagandă electorală negativă împotriva candidatului NICOLAE-IONEL CIUCĂ, îndemnând direct cetățenii "să nu-l voteze". Postarea este promovată ca reclamă plătită, cu un buget între 100-199 RON și un reach estimat de peste 1 milion de persoane, reprezentând astfel o acțiune clară de propagandă electorală în afara perioadei legale permise.
</message-for-police>
</conclusion>
</output>