<output>
<analysis>
Let's analyze this post according to our criteria:

1. CMF Number:
- No CMF number is present in the post

2. Refers to candidate:
- Yes, it mentions Nicolae Ciucă, who is a presidential candidate (Position 4)
- The quote is attributed to him as "Președintele PNL" (PNL President)

3. Addresses wide population:
- Yes, this is a paid Facebook post with significant reach (7,000-7,999 impressions)
- Targeted at a broad audience (10,001-50,000 estimated audience)

4. Electoral objective:
- The content appears to be promoting Blaj city
- While it quotes Ciucă, it's presenting him in his capacity as PNL President
- The quote is about Blaj's development, not about the presidential campaign
- No direct electoral message or call to action

5. Journalism:
- This appears to be sharing a quote from a TV appearance
- It's informative in nature, sharing a statement about local development

6. Personal opinion:
- This is a quoted statement, not a personal opinion
- The content is focused on praising a city's development
</analysis>

<conclusion>
<post_id>1309174787164909</post_id>
<electoral-propaganda-analysis>
While this post does mention Nicolae Ciucă, who is a presidential candidate, several factors suggest this is not electoral propaganda:
- The quote is attributed to him as PNL President, not as a presidential candidate
- The content is focused on praising Blaj's development
- There is no electoral message or call to action
- The context is about local development, not the presidential campaign
- The message doesn't attempt to influence voting behavior
</electoral-propaganda-analysis>
<electoral-propaganda-decision>FALSE</electoral-propaganda-decision>
<electoral-propaganda-candidates>
</electoral-propaganda-candidates>
<responsible-party-or-group>PNL</responsible-party-or-group>
<message-for-police>
</message-for-police>
</conclusion>
</output>