<output>
<analysis>
Let me analyze this post according to the given criteria:

1. CMF Number:
- Contains CMF 11240002, indicating it's electoral propaganda

2. Refers to candidate:
- Explicitly mentions Nicolae Ciucă, who is a presidential candidate
- Presents him as "un lider de excepție"
- Recommends him as "alegerea ideală pentru funcția de Președinte al României"

3. Addresses wide population:
- It's a paid advertisement on Facebook and Instagram
- Uses inclusive language ("Împreună", "vă prezentăm")
- Targets a broad audience (estimated 1001-5000 people)

4. Electoral objective:
- Clearly aims to influence voters for both parliamentary and presidential elections
- Explicitly promotes Nicolae Ciucă for the presidential position
- Uses campaign slogans and calls to action

5. Journalism vs Propaganda:
- This is clearly campaign material, not journalism
- Contains party slogans and campaign hashtags
- Promotes both party and candidate

6. Personal Opinion:
- This is not a personal opinion but an official party communication
- Contains official CMF number
- Structured as campaign material
</analysis>

<conclusion>
<post_id>1290694521930956</post_id>
<electoral-propaganda-analysis>
This post constitutes electoral propaganda because:
1. It contains an official CMF number
2. Explicitly promotes a presidential candidate
3. Is structured as campaign material
4. Has clear electoral objectives
5. Is being distributed as paid advertising after the end of the presidential campaign period
</electoral-propaganda-analysis>
<electoral-propaganda-decision>TRUE</electoral-propaganda-decision>
<electoral-propaganda-candidates>
<candidate>
<name>NICOLAE-IONEL CIUCĂ</name>
<impact>POSITIVE</impact>
</candidate>
</electoral-propaganda-candidates>
<responsible-party-or-group>PNL</responsible-party-or-group>
<message-for-police>
Partidul Național Liberal (PNL) și Ucu Dima, pentru incalcarea articolului 55 t) din Legea 370/2004, prin difuzarea de materiale de propagandă electorală după încheierea perioadei de campanie pentru alegerile prezidențiale. Postarea cu ID-ul 1290694521930956 promovează explicit candidatul Nicolae Ciucă pentru funcția de președinte, prezentându-l ca "lider de excepție" și "alegerea ideală pentru funcția de Președinte al României", având un evident caracter de propagandă electorală demonstrat prin prezența numărului CMF 11240002, natura plătită a postării și distribuirea acesteia după ora 18:00 pe 23.11.2024. Mesajul are un efect electoral direct, încercând să influențeze alegătorii în favoarea candidatului PNL la președinție, depășind limitele comunicării permise în această perioadă.
</message-for-police>
</conclusion>
</output>