<output>
<analysis>
Let me analyze this post according to our criteria:

1. Has CMF: No visible CMF number, but this isn't conclusive by itself.

2. Refers to candidate: Yes, explicitly mentions "Elena Lasconi" who is a presidential candidate (Position #1).

3. Addresses wide population: Yes, this is a paid advertisement on Facebook/Instagram with significant reach (4,000-4,999 impressions).

4. Electoral objective: Yes, the content clearly promotes Elena Lasconi's presidential candidacy by highlighting her qualities as a potential president ("viziune clară pentru viitorul acestei țări").

5. Journalism: No, this is a direct quote promoting a candidate, not journalistic content.

6. Personal opinion: While it's presented as Dan Ivan's opinion, it's being promoted as a paid advertisement with clear electoral intent.

The post contains direct promotional content for a presidential candidate after the campaign period has ended, which is specifically prohibited.
</analysis>

<conclusion>
<post_id>1077556713676876</post_id>
<electoral-propaganda-analysis>
This is clearly electoral propaganda because:
- Directly promotes a presidential candidate
- Highlights qualities relevant to the presidential role
- Is a paid advertisement reaching thousands
- Attempts to influence public opinion during the electoral silence period
- Goes beyond simple information sharing into promotional territory
</electoral-propaganda-analysis>
<electoral-propaganda-decision>TRUE</electoral-propaganda-decision>
<electoral-propaganda-candidates>
  <candidate>
    <name>ELENA-VALERICA LASCONI</name>
    <impact>POSITIVE</impact>
  </candidate>
</electoral-propaganda-candidates>
<responsible-party-or-group>USR</responsible-party-or-group>
<message-for-police>
Maramures INFO News, pentru incalcarea articolului 55 t) din Legea 370/2004, prin promovarea unui mesaj de propaganda electorala pentru candidatul USR la prezidentiale Elena Lasconi, dupa incheierea perioadei de campanie electorala, prin intermediul unei reclame platite pe Facebook si Instagram (ID: 1077556713676876). Postarea promoveaza in mod explicit candidatul ("Elena Lasconi nu doar că este o femeie cu o viziune clară pentru viitorul acestei țări"), prezentand caracteristici relevante pentru functia de presedinte si urmarind influentarea intentiei de vot a publicului larg, dupa ora 18:00 pe 23.11.2024, prin intermediul unei reclame cu impact semnificativ (4000-4999 impresii). Caracterul electoral al mesajului este evident prin referirea directa la calitațile de conducator si la viitorul țării, in contextul alegerilor prezidentiale.
</message-for-police>
</conclusion>
</output>