<output>
<analysis>
Let's analyze this post according to our criteria:

1. Has CMF: No visible CMF number, but this doesn't automatically disqualify it as propaganda.

2. Refers to candidate: Yes, mentions "Simion" and "Sergiu Mihalcea" specifically.

3. Addresses wide population: Yes, this is a paid Facebook/Instagram advertisement with potential reach of over 1 million people.

4. Electoral objective: Yes, but specifically for parliamentary elections:
- Promotes Sergiu Mihalcea for Senate (Ilfov)
- Uses "Votează" (Vote) call to action
- References "Planul Simion" but in context of parliamentary candidate

5. Journalism: No, this is clearly campaign material.

6. Personal opinion: No, this is organized campaign communication.

Key point: While this mentions Simion, it's in context of parliamentary elections which are still in their legal campaign period. The main focus is on Sergiu Mihalcea's Senate candidacy.
</analysis>

<conclusion>
<post_id>595806476201989</post_id>
<electoral-propaganda-analysis>
This post constitutes electoral propaganda, but for the parliamentary elections which are still in their legal campaign period. While it mentions Simion, it does so in context of party leadership rather than presidential candidacy. The main promotional focus is on Sergiu Mihalcea for Senate.
</electoral-propaganda-analysis>
<electoral-propaganda-decision>FALSE</electoral-propaganda-decision>
<electoral-propaganda-candidates>
</electoral-propaganda-candidates>
<responsible-party-or-group>AUR</responsible-party-or-group>
<message-for-police>
</message-for-police>
</conclusion>
</output>